[
  {
    "CountyName": "Accomack",
    "TotalMatchedVoters": 2307,
    "DemVotedCount": 929,
    "RepVotedCount": 533,
    "UnknownVotedCount": 46,
    "InPersonCount": 1224,
    "MailCount": 302,
    "InPersonDem": 735,
    "InPersonRep": 440,
    "MailDem": 194,
    "MailRep": 93,
    "DemOutCount": 399,
    "RepOutCount": 291,
    "UnknownOutCount": 48,
    "VotedCount": 1508,
    "OutCount": 738
  },
  {
    "CountyName": "Albemarle",
    "TotalMatchedVoters": 10487,
    "DemVotedCount": 2903,
    "RepVotedCount": 980,
    "UnknownVotedCount": 153,
    "InPersonCount": 3526,
    "MailCount": 541,
    "InPersonDem": 2459,
    "InPersonRep": 901,
    "MailDem": 443,
    "MailRep": 79,
    "DemOutCount": 4971,
    "RepOutCount": 885,
    "UnknownOutCount": 351,
    "VotedCount": 4036,
    "OutCount": 6207
  },
  {
    "CountyName": "Alexandria (City)",
    "TotalMatchedVoters": 12235,
    "DemVotedCount": 4349,
    "RepVotedCount": 586,
    "UnknownVotedCount": 82,
    "InPersonCount": 2300,
    "MailCount": 2757,
    "InPersonDem": 1940,
    "InPersonRep": 305,
    "MailDem": 2409,
    "MailRep": 281,
    "DemOutCount": 6195,
    "RepOutCount": 588,
    "UnknownOutCount": 121,
    "VotedCount": 5017,
    "OutCount": 6904
  },
  {
    "CountyName": "Alleghany",
    "TotalMatchedVoters": 674,
    "DemVotedCount": 192,
    "RepVotedCount": 239,
    "UnknownVotedCount": 5,
    "InPersonCount": 320,
    "MailCount": 124,
    "InPersonDem": 125,
    "InPersonRep": 185,
    "MailDem": 67,
    "MailRep": 54,
    "DemOutCount": 97,
    "RepOutCount": 116,
    "UnknownOutCount": 5,
    "VotedCount": 436,
    "OutCount": 218
  },
  {
    "CountyName": "Amelia",
    "TotalMatchedVoters": 865,
    "DemVotedCount": 194,
    "RepVotedCount": 417,
    "UnknownVotedCount": 13,
    "InPersonCount": 536,
    "MailCount": 91,
    "InPersonDem": 143,
    "InPersonRep": 382,
    "MailDem": 51,
    "MailRep": 35,
    "DemOutCount": 117,
    "RepOutCount": 99,
    "UnknownOutCount": 11,
    "VotedCount": 624,
    "OutCount": 227
  },
  {
    "CountyName": "Amherst",
    "TotalMatchedVoters": 2063,
    "DemVotedCount": 458,
    "RepVotedCount": 786,
    "UnknownVotedCount": 24,
    "InPersonCount": 963,
    "MailCount": 318,
    "InPersonDem": 296,
    "InPersonRep": 637,
    "MailDem": 162,
    "MailRep": 149,
    "DemOutCount": 399,
    "RepOutCount": 331,
    "UnknownOutCount": 35,
    "VotedCount": 1268,
    "OutCount": 765
  },
  {
    "CountyName": "Appomattox",
    "TotalMatchedVoters": 1108,
    "DemVotedCount": 236,
    "RepVotedCount": 611,
    "UnknownVotedCount": 14,
    "InPersonCount": 770,
    "MailCount": 109,
    "InPersonDem": 172,
    "InPersonRep": 572,
    "MailDem": 64,
    "MailRep": 39,
    "DemOutCount": 90,
    "RepOutCount": 119,
    "UnknownOutCount": 8,
    "VotedCount": 861,
    "OutCount": 217
  },
  {
    "CountyName": "Arlington",
    "TotalMatchedVoters": 17843,
    "DemVotedCount": 5424,
    "RepVotedCount": 572,
    "UnknownVotedCount": 78,
    "InPersonCount": 3348,
    "MailCount": 2764,
    "InPersonDem": 2968,
    "InPersonRep": 318,
    "MailDem": 2456,
    "MailRep": 254,
    "DemOutCount": 10075,
    "RepOutCount": 910,
    "UnknownOutCount": 187,
    "VotedCount": 6074,
    "OutCount": 11172
  },
  {
    "CountyName": "Augusta",
    "TotalMatchedVoters": 4811,
    "DemVotedCount": 821,
    "RepVotedCount": 2194,
    "UnknownVotedCount": 51,
    "InPersonCount": 2698,
    "MailCount": 411,
    "InPersonDem": 631,
    "InPersonRep": 1981,
    "MailDem": 189,
    "MailRep": 213,
    "DemOutCount": 658,
    "RepOutCount": 905,
    "UnknownOutCount": 69,
    "VotedCount": 3066,
    "OutCount": 1632
  },
  {
    "CountyName": "Bath",
    "TotalMatchedVoters": 237,
    "DemVotedCount": 37,
    "RepVotedCount": 99,
    "UnknownVotedCount": 2,
    "InPersonCount": 130,
    "MailCount": 10,
    "InPersonDem": 35,
    "InPersonRep": 91,
    "MailDem": 2,
    "MailRep": 8,
    "DemOutCount": 32,
    "RepOutCount": 57,
    "UnknownOutCount": 0,
    "VotedCount": 138,
    "OutCount": 89
  },
  {
    "CountyName": "Bedford",
    "TotalMatchedVoters": 5582,
    "DemVotedCount": 1058,
    "RepVotedCount": 2501,
    "UnknownVotedCount": 62,
    "InPersonCount": 2787,
    "MailCount": 882,
    "InPersonDem": 621,
    "InPersonRep": 2089,
    "MailDem": 437,
    "MailRep": 412,
    "DemOutCount": 784,
    "RepOutCount": 963,
    "UnknownOutCount": 54,
    "VotedCount": 3621,
    "OutCount": 1801
  },
  {
    "CountyName": "Bland",
    "TotalMatchedVoters": 266,
    "DemVotedCount": 63,
    "RepVotedCount": 113,
    "UnknownVotedCount": 0,
    "InPersonCount": 137,
    "MailCount": 47,
    "InPersonDem": 42,
    "InPersonRep": 88,
    "MailDem": 21,
    "MailRep": 25,
    "DemOutCount": 42,
    "RepOutCount": 36,
    "UnknownOutCount": 2,
    "VotedCount": 176,
    "OutCount": 80
  },
  {
    "CountyName": "Botetourt",
    "TotalMatchedVoters": 2403,
    "DemVotedCount": 564,
    "RepVotedCount": 1082,
    "UnknownVotedCount": 26,
    "InPersonCount": 1323,
    "MailCount": 369,
    "InPersonDem": 390,
    "InPersonRep": 895,
    "MailDem": 174,
    "MailRep": 187,
    "DemOutCount": 271,
    "RepOutCount": 379,
    "UnknownOutCount": 21,
    "VotedCount": 1672,
    "OutCount": 671
  },
  {
    "CountyName": "Bristol (City)",
    "TotalMatchedVoters": 830,
    "DemVotedCount": 190,
    "RepVotedCount": 273,
    "UnknownVotedCount": 15,
    "InPersonCount": 265,
    "MailCount": 219,
    "InPersonDem": 79,
    "InPersonRep": 179,
    "MailDem": 111,
    "MailRep": 94,
    "DemOutCount": 145,
    "RepOutCount": 189,
    "UnknownOutCount": 7,
    "VotedCount": 478,
    "OutCount": 341
  },
  {
    "CountyName": "Brunswick",
    "TotalMatchedVoters": 940,
    "DemVotedCount": 373,
    "RepVotedCount": 169,
    "UnknownVotedCount": 18,
    "InPersonCount": 393,
    "MailCount": 169,
    "InPersonDem": 250,
    "InPersonRep": 129,
    "MailDem": 123,
    "MailRep": 40,
    "DemOutCount": 274,
    "RepOutCount": 73,
    "UnknownOutCount": 20,
    "VotedCount": 560,
    "OutCount": 367
  },
  {
    "CountyName": "Buchanan",
    "TotalMatchedVoters": 542,
    "DemVotedCount": 88,
    "RepVotedCount": 215,
    "UnknownVotedCount": 1,
    "InPersonCount": 214,
    "MailCount": 101,
    "InPersonDem": 37,
    "InPersonRep": 165,
    "MailDem": 51,
    "MailRep": 50,
    "DemOutCount": 82,
    "RepOutCount": 135,
    "UnknownOutCount": 2,
    "VotedCount": 304,
    "OutCount": 219
  },
  {
    "CountyName": "Buckingham",
    "TotalMatchedVoters": 1041,
    "DemVotedCount": 280,
    "RepVotedCount": 391,
    "UnknownVotedCount": 11,
    "InPersonCount": 596,
    "MailCount": 95,
    "InPersonDem": 213,
    "InPersonRep": 367,
    "MailDem": 67,
    "MailRep": 24,
    "DemOutCount": 209,
    "RepOutCount": 108,
    "UnknownOutCount": 23,
    "VotedCount": 682,
    "OutCount": 340
  },
  {
    "CountyName": "Buena Vista (City)",
    "TotalMatchedVoters": 356,
    "DemVotedCount": 90,
    "RepVotedCount": 146,
    "UnknownVotedCount": 1,
    "InPersonCount": 189,
    "MailCount": 50,
    "InPersonDem": 61,
    "InPersonRep": 127,
    "MailDem": 29,
    "MailRep": 19,
    "DemOutCount": 58,
    "RepOutCount": 51,
    "UnknownOutCount": 2,
    "VotedCount": 237,
    "OutCount": 111
  },
  {
    "CountyName": "Campbell",
    "TotalMatchedVoters": 3334,
    "DemVotedCount": 396,
    "RepVotedCount": 1408,
    "UnknownVotedCount": 22,
    "InPersonCount": 1629,
    "MailCount": 222,
    "InPersonDem": 297,
    "InPersonRep": 1297,
    "MailDem": 99,
    "MailRep": 111,
    "DemOutCount": 643,
    "RepOutCount": 726,
    "UnknownOutCount": 68,
    "VotedCount": 1826,
    "OutCount": 1437
  },
  {
    "CountyName": "Caroline",
    "TotalMatchedVoters": 2093,
    "DemVotedCount": 500,
    "RepVotedCount": 525,
    "UnknownVotedCount": 35,
    "InPersonCount": 897,
    "MailCount": 178,
    "InPersonDem": 375,
    "InPersonRep": 480,
    "MailDem": 125,
    "MailRep": 45,
    "DemOutCount": 630,
    "RepOutCount": 261,
    "UnknownOutCount": 82,
    "VotedCount": 1060,
    "OutCount": 973
  },
  {
    "CountyName": "Carroll",
    "TotalMatchedVoters": 1506,
    "DemVotedCount": 321,
    "RepVotedCount": 697,
    "UnknownVotedCount": 18,
    "InPersonCount": 659,
    "MailCount": 394,
    "InPersonDem": 154,
    "InPersonRep": 484,
    "MailDem": 167,
    "MailRep": 213,
    "DemOutCount": 140,
    "RepOutCount": 285,
    "UnknownOutCount": 10,
    "VotedCount": 1036,
    "OutCount": 435
  },
  {
    "CountyName": "Charles City",
    "TotalMatchedVoters": 663,
    "DemVotedCount": 281,
    "RepVotedCount": 108,
    "UnknownVotedCount": 14,
    "InPersonCount": 229,
    "MailCount": 175,
    "InPersonDem": 143,
    "InPersonRep": 76,
    "MailDem": 138,
    "MailRep": 32,
    "DemOutCount": 198,
    "RepOutCount": 39,
    "UnknownOutCount": 17,
    "VotedCount": 403,
    "OutCount": 254
  },
  {
    "CountyName": "Charlotte",
    "TotalMatchedVoters": 592,
    "DemVotedCount": 160,
    "RepVotedCount": 210,
    "UnknownVotedCount": 6,
    "InPersonCount": 318,
    "MailCount": 63,
    "InPersonDem": 117,
    "InPersonRep": 191,
    "MailDem": 43,
    "MailRep": 19,
    "DemOutCount": 99,
    "RepOutCount": 86,
    "UnknownOutCount": 11,
    "VotedCount": 376,
    "OutCount": 196
  },
  {
    "CountyName": "Charlottesville (City)",
    "TotalMatchedVoters": 3214,
    "DemVotedCount": 1284,
    "RepVotedCount": 93,
    "UnknownVotedCount": 9,
    "InPersonCount": 1112,
    "MailCount": 283,
    "InPersonDem": 1018,
    "InPersonRep": 80,
    "MailDem": 266,
    "MailRep": 13,
    "DemOutCount": 1632,
    "RepOutCount": 113,
    "UnknownOutCount": 23,
    "VotedCount": 1386,
    "OutCount": 1768
  },
  {
    "CountyName": "Chesapeake (City)",
    "TotalMatchedVoters": 16776,
    "DemVotedCount": 3645,
    "RepVotedCount": 2819,
    "UnknownVotedCount": 321,
    "InPersonCount": 5060,
    "MailCount": 1807,
    "InPersonDem": 2473,
    "InPersonRep": 2323,
    "MailDem": 1172,
    "MailRep": 496,
    "DemOutCount": 6154,
    "RepOutCount": 2489,
    "UnknownOutCount": 971,
    "VotedCount": 6785,
    "OutCount": 9614
  },
  {
    "CountyName": "Chesterfield",
    "TotalMatchedVoters": 27754,
    "DemVotedCount": 6337,
    "RepVotedCount": 4811,
    "UnknownVotedCount": 588,
    "InPersonCount": 7730,
    "MailCount": 4111,
    "InPersonDem": 3831,
    "InPersonRep": 3512,
    "MailDem": 2506,
    "MailRep": 1299,
    "DemOutCount": 9937,
    "RepOutCount": 3870,
    "UnknownOutCount": 1611,
    "VotedCount": 11736,
    "OutCount": 15418
  },
  {
    "CountyName": "Clarke",
    "TotalMatchedVoters": 1406,
    "DemVotedCount": 511,
    "RepVotedCount": 490,
    "UnknownVotedCount": 26,
    "InPersonCount": 864,
    "MailCount": 175,
    "InPersonDem": 403,
    "InPersonRep": 429,
    "MailDem": 107,
    "MailRep": 61,
    "DemOutCount": 191,
    "RepOutCount": 125,
    "UnknownOutCount": 23,
    "VotedCount": 1027,
    "OutCount": 339
  },
  {
    "CountyName": "Colonial Heights (City)",
    "TotalMatchedVoters": 1158,
    "DemVotedCount": 205,
    "RepVotedCount": 536,
    "UnknownVotedCount": 21,
    "InPersonCount": 603,
    "MailCount": 169,
    "InPersonDem": 136,
    "InPersonRep": 439,
    "MailDem": 69,
    "MailRep": 97,
    "DemOutCount": 141,
    "RepOutCount": 205,
    "UnknownOutCount": 21,
    "VotedCount": 762,
    "OutCount": 367
  },
  {
    "CountyName": "Covington (City)",
    "TotalMatchedVoters": 170,
    "DemVotedCount": 56,
    "RepVotedCount": 61,
    "UnknownVotedCount": 3,
    "InPersonCount": 81,
    "MailCount": 41,
    "InPersonDem": 31,
    "InPersonRep": 47,
    "MailDem": 25,
    "MailRep": 14,
    "DemOutCount": 26,
    "RepOutCount": 13,
    "UnknownOutCount": 7,
    "VotedCount": 120,
    "OutCount": 46
  },
  {
    "CountyName": "Craig",
    "TotalMatchedVoters": 300,
    "DemVotedCount": 51,
    "RepVotedCount": 193,
    "UnknownVotedCount": 3,
    "InPersonCount": 206,
    "MailCount": 41,
    "InPersonDem": 31,
    "InPersonRep": 172,
    "MailDem": 20,
    "MailRep": 21,
    "DemOutCount": 18,
    "RepOutCount": 32,
    "UnknownOutCount": 0,
    "VotedCount": 247,
    "OutCount": 50
  },
  {
    "CountyName": "Culpeper",
    "TotalMatchedVoters": 3987,
    "DemVotedCount": 1034,
    "RepVotedCount": 1197,
    "UnknownVotedCount": 81,
    "InPersonCount": 1673,
    "MailCount": 655,
    "InPersonDem": 674,
    "InPersonRep": 933,
    "MailDem": 360,
    "MailRep": 264,
    "DemOutCount": 885,
    "RepOutCount": 592,
    "UnknownOutCount": 109,
    "VotedCount": 2312,
    "OutCount": 1586
  },
  {
    "CountyName": "Cumberland",
    "TotalMatchedVoters": 589,
    "DemVotedCount": 186,
    "RepVotedCount": 189,
    "UnknownVotedCount": 9,
    "InPersonCount": 326,
    "MailCount": 62,
    "InPersonDem": 141,
    "InPersonRep": 173,
    "MailDem": 45,
    "MailRep": 16,
    "DemOutCount": 102,
    "RepOutCount": 82,
    "UnknownOutCount": 12,
    "VotedCount": 384,
    "OutCount": 196
  },
  {
    "CountyName": "Danville (City)",
    "TotalMatchedVoters": 2454,
    "DemVotedCount": 922,
    "RepVotedCount": 512,
    "UnknownVotedCount": 44,
    "InPersonCount": 931,
    "MailCount": 555,
    "InPersonDem": 538,
    "InPersonRep": 362,
    "MailDem": 384,
    "MailRep": 150,
    "DemOutCount": 689,
    "RepOutCount": 161,
    "UnknownOutCount": 92,
    "VotedCount": 1478,
    "OutCount": 942
  },
  {
    "CountyName": "Dickenson",
    "TotalMatchedVoters": 645,
    "DemVotedCount": 134,
    "RepVotedCount": 259,
    "UnknownVotedCount": 1,
    "InPersonCount": 293,
    "MailCount": 106,
    "InPersonDem": 80,
    "InPersonRep": 208,
    "MailDem": 54,
    "MailRep": 51,
    "DemOutCount": 93,
    "RepOutCount": 140,
    "UnknownOutCount": 1,
    "VotedCount": 394,
    "OutCount": 234
  },
  {
    "CountyName": "Dinwiddie",
    "TotalMatchedVoters": 1790,
    "DemVotedCount": 509,
    "RepVotedCount": 508,
    "UnknownVotedCount": 17,
    "InPersonCount": 833,
    "MailCount": 213,
    "InPersonDem": 390,
    "InPersonRep": 422,
    "MailDem": 119,
    "MailRep": 86,
    "DemOutCount": 439,
    "RepOutCount": 259,
    "UnknownOutCount": 21,
    "VotedCount": 1034,
    "OutCount": 719
  },
  {
    "CountyName": "Emporia (City)",
    "TotalMatchedVoters": 286,
    "DemVotedCount": 78,
    "RepVotedCount": 32,
    "UnknownVotedCount": 5,
    "InPersonCount": 97,
    "MailCount": 18,
    "InPersonDem": 66,
    "InPersonRep": 27,
    "MailDem": 12,
    "MailRep": 5,
    "DemOutCount": 140,
    "RepOutCount": 24,
    "UnknownOutCount": 7,
    "VotedCount": 115,
    "OutCount": 171
  },
  {
    "CountyName": "Essex",
    "TotalMatchedVoters": 782,
    "DemVotedCount": 207,
    "RepVotedCount": 283,
    "UnknownVotedCount": 10,
    "InPersonCount": 472,
    "MailCount": 37,
    "InPersonDem": 181,
    "InPersonRep": 272,
    "MailDem": 26,
    "MailRep": 11,
    "DemOutCount": 148,
    "RepOutCount": 79,
    "UnknownOutCount": 32,
    "VotedCount": 500,
    "OutCount": 259
  },
  {
    "CountyName": "Fairfax",
    "TotalMatchedVoters": 84753,
    "DemVotedCount": 18289,
    "RepVotedCount": 5740,
    "UnknownVotedCount": 1098,
    "InPersonCount": 12435,
    "MailCount": 12947,
    "InPersonDem": 8160,
    "InPersonRep": 3624,
    "MailDem": 10128,
    "MailRep": 2116,
    "DemOutCount": 46237,
    "RepOutCount": 7455,
    "UnknownOutCount": 3430,
    "VotedCount": 25127,
    "OutCount": 57122
  },
  {
    "CountyName": "Fairfax (City)",
    "TotalMatchedVoters": 2192,
    "DemVotedCount": 870,
    "RepVotedCount": 262,
    "UnknownVotedCount": 48,
    "InPersonCount": 739,
    "MailCount": 448,
    "InPersonDem": 500,
    "InPersonRep": 202,
    "MailDem": 370,
    "MailRep": 60,
    "DemOutCount": 811,
    "RepOutCount": 105,
    "UnknownOutCount": 66,
    "VotedCount": 1180,
    "OutCount": 982
  },
  {
    "CountyName": "Falls Church (City)",
    "TotalMatchedVoters": 1592,
    "DemVotedCount": 782,
    "RepVotedCount": 102,
    "UnknownVotedCount": 9,
    "InPersonCount": 580,
    "MailCount": 325,
    "InPersonDem": 494,
    "InPersonRep": 73,
    "MailDem": 288,
    "MailRep": 29,
    "DemOutCount": 590,
    "RepOutCount": 65,
    "UnknownOutCount": 9,
    "VotedCount": 893,
    "OutCount": 664
  },
  {
    "CountyName": "Fauquier",
    "TotalMatchedVoters": 5703,
    "DemVotedCount": 1566,
    "RepVotedCount": 1850,
    "UnknownVotedCount": 121,
    "InPersonCount": 2422,
    "MailCount": 1153,
    "InPersonDem": 911,
    "InPersonRep": 1410,
    "MailDem": 655,
    "MailRep": 440,
    "DemOutCount": 1052,
    "RepOutCount": 815,
    "UnknownOutCount": 154,
    "VotedCount": 3537,
    "OutCount": 2021
  },
  {
    "CountyName": "Floyd",
    "TotalMatchedVoters": 1213,
    "DemVotedCount": 381,
    "RepVotedCount": 470,
    "UnknownVotedCount": 16,
    "InPersonCount": 681,
    "MailCount": 193,
    "InPersonDem": 272,
    "InPersonRep": 387,
    "MailDem": 109,
    "MailRep": 83,
    "DemOutCount": 176,
    "RepOutCount": 138,
    "UnknownOutCount": 8,
    "VotedCount": 867,
    "OutCount": 322
  },
  {
    "CountyName": "Fluvanna",
    "TotalMatchedVoters": 2932,
    "DemVotedCount": 1063,
    "RepVotedCount": 840,
    "UnknownVotedCount": 93,
    "InPersonCount": 1562,
    "MailCount": 465,
    "InPersonDem": 739,
    "InPersonRep": 739,
    "MailDem": 324,
    "MailRep": 101,
    "DemOutCount": 560,
    "RepOutCount": 233,
    "UnknownOutCount": 92,
    "VotedCount": 1996,
    "OutCount": 885
  },
  {
    "CountyName": "Franklin",
    "TotalMatchedVoters": 3675,
    "DemVotedCount": 858,
    "RepVotedCount": 1461,
    "UnknownVotedCount": 37,
    "InPersonCount": 1922,
    "MailCount": 461,
    "InPersonDem": 655,
    "InPersonRep": 1219,
    "MailDem": 203,
    "MailRep": 241,
    "DemOutCount": 530,
    "RepOutCount": 659,
    "UnknownOutCount": 34,
    "VotedCount": 2356,
    "OutCount": 1223
  },
  {
    "CountyName": "Franklin (City)",
    "TotalMatchedVoters": 502,
    "DemVotedCount": 136,
    "RepVotedCount": 57,
    "UnknownVotedCount": 6,
    "InPersonCount": 153,
    "MailCount": 49,
    "InPersonDem": 96,
    "InPersonRep": 51,
    "MailDem": 40,
    "MailRep": 6,
    "DemOutCount": 236,
    "RepOutCount": 47,
    "UnknownOutCount": 14,
    "VotedCount": 199,
    "OutCount": 297
  },
  {
    "CountyName": "Frederick",
    "TotalMatchedVoters": 6705,
    "DemVotedCount": 1721,
    "RepVotedCount": 2607,
    "UnknownVotedCount": 160,
    "InPersonCount": 3533,
    "MailCount": 1008,
    "InPersonDem": 1204,
    "InPersonRep": 2193,
    "MailDem": 516,
    "MailRep": 414,
    "DemOutCount": 1005,
    "RepOutCount": 886,
    "UnknownOutCount": 171,
    "VotedCount": 4488,
    "OutCount": 2062
  },
  {
    "CountyName": "Fredericksburg (City)",
    "TotalMatchedVoters": 2246,
    "DemVotedCount": 658,
    "RepVotedCount": 261,
    "UnknownVotedCount": 37,
    "InPersonCount": 757,
    "MailCount": 207,
    "InPersonDem": 503,
    "InPersonRep": 220,
    "MailDem": 155,
    "MailRep": 41,
    "DemOutCount": 991,
    "RepOutCount": 185,
    "UnknownOutCount": 71,
    "VotedCount": 956,
    "OutCount": 1247
  },
  {
    "CountyName": "Galax (City)",
    "TotalMatchedVoters": 343,
    "DemVotedCount": 98,
    "RepVotedCount": 154,
    "UnknownVotedCount": 6,
    "InPersonCount": 196,
    "MailCount": 65,
    "InPersonDem": 67,
    "InPersonRep": 121,
    "MailDem": 31,
    "MailRep": 33,
    "DemOutCount": 37,
    "RepOutCount": 40,
    "UnknownOutCount": 3,
    "VotedCount": 258,
    "OutCount": 80
  },
  {
    "CountyName": "Giles",
    "TotalMatchedVoters": 1080,
    "DemVotedCount": 310,
    "RepVotedCount": 559,
    "UnknownVotedCount": 6,
    "InPersonCount": 736,
    "MailCount": 149,
    "InPersonDem": 242,
    "InPersonRep": 483,
    "MailDem": 68,
    "MailRep": 76,
    "DemOutCount": 77,
    "RepOutCount": 112,
    "UnknownOutCount": 1,
    "VotedCount": 875,
    "OutCount": 190
  },
  {
    "CountyName": "Gloucester",
    "TotalMatchedVoters": 2606,
    "DemVotedCount": 655,
    "RepVotedCount": 1157,
    "UnknownVotedCount": 44,
    "InPersonCount": 1507,
    "MailCount": 368,
    "InPersonDem": 484,
    "InPersonRep": 975,
    "MailDem": 171,
    "MailRep": 182,
    "DemOutCount": 327,
    "RepOutCount": 358,
    "UnknownOutCount": 18,
    "VotedCount": 1856,
    "OutCount": 703
  },
  {
    "CountyName": "Goochland",
    "TotalMatchedVoters": 3277,
    "DemVotedCount": 860,
    "RepVotedCount": 1120,
    "UnknownVotedCount": 69,
    "InPersonCount": 1767,
    "MailCount": 304,
    "InPersonDem": 700,
    "InPersonRep": 992,
    "MailDem": 160,
    "MailRep": 128,
    "DemOutCount": 605,
    "RepOutCount": 472,
    "UnknownOutCount": 72,
    "VotedCount": 2049,
    "OutCount": 1149
  },
  {
    "CountyName": "Grayson",
    "TotalMatchedVoters": 720,
    "DemVotedCount": 145,
    "RepVotedCount": 333,
    "UnknownVotedCount": 7,
    "InPersonCount": 325,
    "MailCount": 163,
    "InPersonDem": 73,
    "InPersonRep": 247,
    "MailDem": 72,
    "MailRep": 86,
    "DemOutCount": 90,
    "RepOutCount": 127,
    "UnknownOutCount": 2,
    "VotedCount": 485,
    "OutCount": 219
  },
  {
    "CountyName": "Greene",
    "TotalMatchedVoters": 1655,
    "DemVotedCount": 459,
    "RepVotedCount": 575,
    "UnknownVotedCount": 30,
    "InPersonCount": 823,
    "MailCount": 251,
    "InPersonDem": 293,
    "InPersonRep": 505,
    "MailDem": 166,
    "MailRep": 70,
    "DemOutCount": 326,
    "RepOutCount": 188,
    "UnknownOutCount": 46,
    "VotedCount": 1064,
    "OutCount": 560
  },
  {
    "CountyName": "Greensville",
    "TotalMatchedVoters": 617,
    "DemVotedCount": 155,
    "RepVotedCount": 135,
    "UnknownVotedCount": 6,
    "InPersonCount": 279,
    "MailCount": 21,
    "InPersonDem": 140,
    "InPersonRep": 129,
    "MailDem": 15,
    "MailRep": 6,
    "DemOutCount": 253,
    "RepOutCount": 50,
    "UnknownOutCount": 11,
    "VotedCount": 296,
    "OutCount": 314
  },
  {
    "CountyName": "Halifax",
    "TotalMatchedVoters": 1929,
    "DemVotedCount": 635,
    "RepVotedCount": 586,
    "UnknownVotedCount": 25,
    "InPersonCount": 968,
    "MailCount": 288,
    "InPersonDem": 453,
    "InPersonRep": 489,
    "MailDem": 182,
    "MailRep": 97,
    "DemOutCount": 431,
    "RepOutCount": 182,
    "UnknownOutCount": 39,
    "VotedCount": 1246,
    "OutCount": 652
  },
  {
    "CountyName": "Hampton (City)",
    "TotalMatchedVoters": 8701,
    "DemVotedCount": 2934,
    "RepVotedCount": 642,
    "UnknownVotedCount": 97,
    "InPersonCount": 2808,
    "MailCount": 879,
    "InPersonDem": 2199,
    "InPersonRep": 531,
    "MailDem": 735,
    "MailRep": 110,
    "DemOutCount": 4034,
    "RepOutCount": 627,
    "UnknownOutCount": 226,
    "VotedCount": 3673,
    "OutCount": 4887
  },
  {
    "CountyName": "Hanover",
    "TotalMatchedVoters": 9037,
    "DemVotedCount": 1670,
    "RepVotedCount": 3269,
    "UnknownVotedCount": 168,
    "InPersonCount": 4269,
    "MailCount": 894,
    "InPersonDem": 1199,
    "InPersonRep": 2896,
    "MailDem": 471,
    "MailRep": 373,
    "DemOutCount": 1755,
    "RepOutCount": 1593,
    "UnknownOutCount": 309,
    "VotedCount": 5107,
    "OutCount": 3657
  },
  {
    "CountyName": "Harrisonburg (City)",
    "TotalMatchedVoters": 1793,
    "DemVotedCount": 804,
    "RepVotedCount": 340,
    "UnknownVotedCount": 70,
    "InPersonCount": 994,
    "MailCount": 231,
    "InPersonDem": 635,
    "InPersonRep": 295,
    "MailDem": 169,
    "MailRep": 45,
    "DemOutCount": 385,
    "RepOutCount": 91,
    "UnknownOutCount": 66,
    "VotedCount": 1214,
    "OutCount": 542
  },
  {
    "CountyName": "Henrico",
    "TotalMatchedVoters": 27081,
    "DemVotedCount": 7121,
    "RepVotedCount": 2996,
    "UnknownVotedCount": 364,
    "InPersonCount": 8473,
    "MailCount": 2080,
    "InPersonDem": 5629,
    "InPersonRep": 2516,
    "MailDem": 1492,
    "MailRep": 480,
    "DemOutCount": 11741,
    "RepOutCount": 3283,
    "UnknownOutCount": 1085,
    "VotedCount": 10481,
    "OutCount": 16109
  },
  {
    "CountyName": "Henry",
    "TotalMatchedVoters": 2849,
    "DemVotedCount": 763,
    "RepVotedCount": 1168,
    "UnknownVotedCount": 47,
    "InPersonCount": 1544,
    "MailCount": 452,
    "InPersonDem": 520,
    "InPersonRep": 976,
    "MailDem": 243,
    "MailRep": 192,
    "DemOutCount": 461,
    "RepOutCount": 331,
    "UnknownOutCount": 46,
    "VotedCount": 1978,
    "OutCount": 838
  },
  {
    "CountyName": "Highland",
    "TotalMatchedVoters": 114,
    "DemVotedCount": 43,
    "RepVotedCount": 36,
    "UnknownVotedCount": 1,
    "InPersonCount": 60,
    "MailCount": 24,
    "InPersonDem": 27,
    "InPersonRep": 29,
    "MailDem": 16,
    "MailRep": 7,
    "DemOutCount": 13,
    "RepOutCount": 11,
    "UnknownOutCount": 1,
    "VotedCount": 80,
    "OutCount": 25
  },
  {
    "CountyName": "Hopewell (City)",
    "TotalMatchedVoters": 1172,
    "DemVotedCount": 431,
    "RepVotedCount": 244,
    "UnknownVotedCount": 28,
    "InPersonCount": 451,
    "MailCount": 252,
    "InPersonDem": 244,
    "InPersonRep": 191,
    "MailDem": 184,
    "MailRep": 50,
    "DemOutCount": 318,
    "RepOutCount": 97,
    "UnknownOutCount": 32,
    "VotedCount": 703,
    "OutCount": 447
  },
  {
    "CountyName": "Isle of Wight",
    "TotalMatchedVoters": 3185,
    "DemVotedCount": 629,
    "RepVotedCount": 690,
    "UnknownVotedCount": 30,
    "InPersonCount": 1265,
    "MailCount": 93,
    "InPersonDem": 573,
    "InPersonRep": 654,
    "MailDem": 55,
    "MailRep": 36,
    "DemOutCount": 979,
    "RepOutCount": 680,
    "UnknownOutCount": 111,
    "VotedCount": 1349,
    "OutCount": 1770
  },
  {
    "CountyName": "James City",
    "TotalMatchedVoters": 10326,
    "DemVotedCount": 3575,
    "RepVotedCount": 2927,
    "UnknownVotedCount": 316,
    "InPersonCount": 5597,
    "MailCount": 1282,
    "InPersonDem": 2759,
    "InPersonRep": 2538,
    "MailDem": 816,
    "MailRep": 389,
    "DemOutCount": 2153,
    "RepOutCount": 844,
    "UnknownOutCount": 355,
    "VotedCount": 6818,
    "OutCount": 3352
  },
  {
    "CountyName": "King George",
    "TotalMatchedVoters": 2175,
    "DemVotedCount": 576,
    "RepVotedCount": 885,
    "UnknownVotedCount": 41,
    "InPersonCount": 1226,
    "MailCount": 301,
    "InPersonDem": 390,
    "InPersonRep": 784,
    "MailDem": 186,
    "MailRep": 101,
    "DemOutCount": 314,
    "RepOutCount": 239,
    "UnknownOutCount": 56,
    "VotedCount": 1502,
    "OutCount": 609
  },
  {
    "CountyName": "King William",
    "TotalMatchedVoters": 1024,
    "DemVotedCount": 221,
    "RepVotedCount": 391,
    "UnknownVotedCount": 12,
    "InPersonCount": 490,
    "MailCount": 141,
    "InPersonDem": 145,
    "InPersonRep": 327,
    "MailDem": 76,
    "MailRep": 64,
    "DemOutCount": 195,
    "RepOutCount": 164,
    "UnknownOutCount": 19,
    "VotedCount": 624,
    "OutCount": 378
  },
  {
    "CountyName": "King and Queen",
    "TotalMatchedVoters": 447,
    "DemVotedCount": 69,
    "RepVotedCount": 124,
    "UnknownVotedCount": 3,
    "InPersonCount": 184,
    "MailCount": 14,
    "InPersonDem": 60,
    "InPersonRep": 119,
    "MailDem": 9,
    "MailRep": 5,
    "DemOutCount": 128,
    "RepOutCount": 102,
    "UnknownOutCount": 9,
    "VotedCount": 196,
    "OutCount": 239
  },
  {
    "CountyName": "Lancaster",
    "TotalMatchedVoters": 1131,
    "DemVotedCount": 316,
    "RepVotedCount": 445,
    "UnknownVotedCount": 34,
    "InPersonCount": 692,
    "MailCount": 109,
    "InPersonDem": 253,
    "InPersonRep": 406,
    "MailDem": 63,
    "MailRep": 39,
    "DemOutCount": 180,
    "RepOutCount": 109,
    "UnknownOutCount": 26,
    "VotedCount": 795,
    "OutCount": 315
  },
  {
    "CountyName": "Lee",
    "TotalMatchedVoters": 702,
    "DemVotedCount": 73,
    "RepVotedCount": 320,
    "UnknownVotedCount": 4,
    "InPersonCount": 334,
    "MailCount": 85,
    "InPersonDem": 44,
    "InPersonRep": 268,
    "MailDem": 29,
    "MailRep": 51,
    "DemOutCount": 65,
    "RepOutCount": 199,
    "UnknownOutCount": 3,
    "VotedCount": 397,
    "OutCount": 267
  },
  {
    "CountyName": "Lexington (City)",
    "TotalMatchedVoters": 511,
    "DemVotedCount": 267,
    "RepVotedCount": 93,
    "UnknownVotedCount": 16,
    "InPersonCount": 281,
    "MailCount": 97,
    "InPersonDem": 183,
    "InPersonRep": 83,
    "MailDem": 84,
    "MailRep": 10,
    "DemOutCount": 94,
    "RepOutCount": 16,
    "UnknownOutCount": 14,
    "VotedCount": 376,
    "OutCount": 124
  },
  {
    "CountyName": "Loudoun",
    "TotalMatchedVoters": 28966,
    "DemVotedCount": 6337,
    "RepVotedCount": 3255,
    "UnknownVotedCount": 671,
    "InPersonCount": 5630,
    "MailCount": 4750,
    "InPersonDem": 3131,
    "InPersonRep": 2118,
    "MailDem": 3206,
    "MailRep": 1137,
    "DemOutCount": 11779,
    "RepOutCount": 3717,
    "UnknownOutCount": 2255,
    "VotedCount": 10263,
    "OutCount": 17751
  },
  {
    "CountyName": "Louisa",
    "TotalMatchedVoters": 3235,
    "DemVotedCount": 784,
    "RepVotedCount": 1048,
    "UnknownVotedCount": 39,
    "InPersonCount": 1542,
    "MailCount": 348,
    "InPersonDem": 569,
    "InPersonRep": 928,
    "MailDem": 215,
    "MailRep": 120,
    "DemOutCount": 727,
    "RepOutCount": 506,
    "UnknownOutCount": 50,
    "VotedCount": 1871,
    "OutCount": 1283
  },
  {
    "CountyName": "Lunenburg",
    "TotalMatchedVoters": 799,
    "DemVotedCount": 312,
    "RepVotedCount": 244,
    "UnknownVotedCount": 13,
    "InPersonCount": 412,
    "MailCount": 160,
    "InPersonDem": 191,
    "InPersonRep": 207,
    "MailDem": 121,
    "MailRep": 37,
    "DemOutCount": 135,
    "RepOutCount": 67,
    "UnknownOutCount": 14,
    "VotedCount": 569,
    "OutCount": 216
  },
  {
    "CountyName": "Lynchburg (City)",
    "TotalMatchedVoters": 5225,
    "DemVotedCount": 1020,
    "RepVotedCount": 808,
    "UnknownVotedCount": 49,
    "InPersonCount": 1877,
    "MailCount": 14,
    "InPersonDem": 1014,
    "InPersonRep": 800,
    "MailDem": 6,
    "MailRep": 8,
    "DemOutCount": 2039,
    "RepOutCount": 984,
    "UnknownOutCount": 243,
    "VotedCount": 1877,
    "OutCount": 3266
  },
  {
    "CountyName": "Madison",
    "TotalMatchedVoters": 1051,
    "DemVotedCount": 282,
    "RepVotedCount": 508,
    "UnknownVotedCount": 11,
    "InPersonCount": 693,
    "MailCount": 116,
    "InPersonDem": 218,
    "InPersonRep": 459,
    "MailDem": 64,
    "MailRep": 49,
    "DemOutCount": 133,
    "RepOutCount": 90,
    "UnknownOutCount": 10,
    "VotedCount": 801,
    "OutCount": 233
  },
  {
    "CountyName": "Manassas (City)",
    "TotalMatchedVoters": 2524,
    "DemVotedCount": 846,
    "RepVotedCount": 380,
    "UnknownVotedCount": 77,
    "InPersonCount": 859,
    "MailCount": 458,
    "InPersonDem": 510,
    "InPersonRep": 293,
    "MailDem": 336,
    "MailRep": 87,
    "DemOutCount": 855,
    "RepOutCount": 196,
    "UnknownOutCount": 134,
    "VotedCount": 1303,
    "OutCount": 1185
  },
  {
    "CountyName": "Manassas Park (City)",
    "TotalMatchedVoters": 837,
    "DemVotedCount": 271,
    "RepVotedCount": 113,
    "UnknownVotedCount": 33,
    "InPersonCount": 257,
    "MailCount": 167,
    "InPersonDem": 143,
    "InPersonRep": 87,
    "MailDem": 128,
    "MailRep": 26,
    "DemOutCount": 283,
    "RepOutCount": 64,
    "UnknownOutCount": 54,
    "VotedCount": 417,
    "OutCount": 401
  },
  {
    "CountyName": "Martinsville (City)",
    "TotalMatchedVoters": 726,
    "DemVotedCount": 303,
    "RepVotedCount": 128,
    "UnknownVotedCount": 32,
    "InPersonCount": 260,
    "MailCount": 210,
    "InPersonDem": 141,
    "InPersonRep": 93,
    "MailDem": 162,
    "MailRep": 35,
    "DemOutCount": 200,
    "RepOutCount": 34,
    "UnknownOutCount": 19,
    "VotedCount": 463,
    "OutCount": 253
  },
  {
    "CountyName": "Mathews",
    "TotalMatchedVoters": 1113,
    "DemVotedCount": 328,
    "RepVotedCount": 588,
    "UnknownVotedCount": 18,
    "InPersonCount": 869,
    "MailCount": 81,
    "InPersonDem": 292,
    "InPersonRep": 548,
    "MailDem": 36,
    "MailRep": 40,
    "DemOutCount": 64,
    "RepOutCount": 86,
    "UnknownOutCount": 4,
    "VotedCount": 934,
    "OutCount": 154
  },
  {
    "CountyName": "Mecklenburg",
    "TotalMatchedVoters": 1764,
    "DemVotedCount": 418,
    "RepVotedCount": 628,
    "UnknownVotedCount": 31,
    "InPersonCount": 753,
    "MailCount": 335,
    "InPersonDem": 241,
    "InPersonRep": 488,
    "MailDem": 177,
    "MailRep": 140,
    "DemOutCount": 419,
    "RepOutCount": 203,
    "UnknownOutCount": 34,
    "VotedCount": 1077,
    "OutCount": 656
  },
  {
    "CountyName": "Middlesex",
    "TotalMatchedVoters": 1111,
    "DemVotedCount": 303,
    "RepVotedCount": 524,
    "UnknownVotedCount": 16,
    "InPersonCount": 770,
    "MailCount": 82,
    "InPersonDem": 255,
    "InPersonRep": 491,
    "MailDem": 48,
    "MailRep": 33,
    "DemOutCount": 104,
    "RepOutCount": 121,
    "UnknownOutCount": 14,
    "VotedCount": 843,
    "OutCount": 239
  },
  {
    "CountyName": "Montgomery",
    "TotalMatchedVoters": 5667,
    "DemVotedCount": 1806,
    "RepVotedCount": 1266,
    "UnknownVotedCount": 147,
    "InPersonCount": 2373,
    "MailCount": 876,
    "InPersonDem": 1201,
    "InPersonRep": 1047,
    "MailDem": 605,
    "MailRep": 219,
    "DemOutCount": 1569,
    "RepOutCount": 511,
    "UnknownOutCount": 239,
    "VotedCount": 3219,
    "OutCount": 2319
  },
  {
    "CountyName": "Nelson",
    "TotalMatchedVoters": 1310,
    "DemVotedCount": 480,
    "RepVotedCount": 322,
    "UnknownVotedCount": 13,
    "InPersonCount": 735,
    "MailCount": 88,
    "InPersonDem": 417,
    "InPersonRep": 299,
    "MailDem": 63,
    "MailRep": 23,
    "DemOutCount": 304,
    "RepOutCount": 142,
    "UnknownOutCount": 28,
    "VotedCount": 815,
    "OutCount": 474
  },
  {
    "CountyName": "New Kent",
    "TotalMatchedVoters": 2039,
    "DemVotedCount": 468,
    "RepVotedCount": 781,
    "UnknownVotedCount": 35,
    "InPersonCount": 1031,
    "MailCount": 263,
    "InPersonDem": 319,
    "InPersonRep": 676,
    "MailDem": 149,
    "MailRep": 105,
    "DemOutCount": 375,
    "RepOutCount": 307,
    "UnknownOutCount": 39,
    "VotedCount": 1284,
    "OutCount": 721
  },
  {
    "CountyName": "Newport News (City)",
    "TotalMatchedVoters": 9152,
    "DemVotedCount": 2359,
    "RepVotedCount": 743,
    "UnknownVotedCount": 137,
    "InPersonCount": 1894,
    "MailCount": 1367,
    "InPersonDem": 1299,
    "InPersonRep": 499,
    "MailDem": 1058,
    "MailRep": 242,
    "DemOutCount": 4479,
    "RepOutCount": 877,
    "UnknownOutCount": 382,
    "VotedCount": 3239,
    "OutCount": 5738
  },
  {
    "CountyName": "Norfolk (City)",
    "TotalMatchedVoters": 11335,
    "DemVotedCount": 2997,
    "RepVotedCount": 512,
    "UnknownVotedCount": 120,
    "InPersonCount": 1379,
    "MailCount": 2270,
    "InPersonDem": 1150,
    "InPersonRep": 187,
    "MailDem": 1847,
    "MailRep": 325,
    "DemOutCount": 6129,
    "RepOutCount": 989,
    "UnknownOutCount": 348,
    "VotedCount": 3629,
    "OutCount": 7466
  },
  {
    "CountyName": "Northampton",
    "TotalMatchedVoters": 1083,
    "DemVotedCount": 454,
    "RepVotedCount": 260,
    "UnknownVotedCount": 31,
    "InPersonCount": 563,
    "MailCount": 188,
    "InPersonDem": 327,
    "InPersonRep": 210,
    "MailDem": 127,
    "MailRep": 49,
    "DemOutCount": 217,
    "RepOutCount": 78,
    "UnknownOutCount": 28,
    "VotedCount": 745,
    "OutCount": 323
  },
  {
    "CountyName": "Northumberland",
    "TotalMatchedVoters": 1210,
    "DemVotedCount": 375,
    "RepVotedCount": 532,
    "UnknownVotedCount": 29,
    "InPersonCount": 819,
    "MailCount": 129,
    "InPersonDem": 304,
    "InPersonRep": 479,
    "MailDem": 71,
    "MailRep": 53,
    "DemOutCount": 150,
    "RepOutCount": 78,
    "UnknownOutCount": 21,
    "VotedCount": 936,
    "OutCount": 249
  },
  {
    "CountyName": "Norton (City)",
    "TotalMatchedVoters": 84,
    "DemVotedCount": 15,
    "RepVotedCount": 10,
    "UnknownVotedCount": 1,
    "InPersonCount": 0,
    "MailCount": 26,
    "InPersonDem": 0,
    "InPersonRep": 0,
    "MailDem": 15,
    "MailRep": 10,
    "DemOutCount": 29,
    "RepOutCount": 27,
    "UnknownOutCount": 1,
    "VotedCount": 26,
    "OutCount": 57
  },
  {
    "CountyName": "Nottoway",
    "TotalMatchedVoters": 661,
    "DemVotedCount": 191,
    "RepVotedCount": 218,
    "UnknownVotedCount": 15,
    "InPersonCount": 315,
    "MailCount": 115,
    "InPersonDem": 128,
    "InPersonRep": 176,
    "MailDem": 63,
    "MailRep": 42,
    "DemOutCount": 113,
    "RepOutCount": 90,
    "UnknownOutCount": 16,
    "VotedCount": 424,
    "OutCount": 219
  },
  {
    "CountyName": "Orange",
    "TotalMatchedVoters": 2848,
    "DemVotedCount": 662,
    "RepVotedCount": 762,
    "UnknownVotedCount": 43,
    "InPersonCount": 1054,
    "MailCount": 429,
    "InPersonDem": 420,
    "InPersonRep": 591,
    "MailDem": 242,
    "MailRep": 171,
    "DemOutCount": 725,
    "RepOutCount": 487,
    "UnknownOutCount": 92,
    "VotedCount": 1467,
    "OutCount": 1304
  },
  {
    "CountyName": "Page",
    "TotalMatchedVoters": 1360,
    "DemVotedCount": 310,
    "RepVotedCount": 579,
    "UnknownVotedCount": 22,
    "InPersonCount": 723,
    "MailCount": 204,
    "InPersonDem": 223,
    "InPersonRep": 469,
    "MailDem": 87,
    "MailRep": 110,
    "DemOutCount": 163,
    "RepOutCount": 242,
    "UnknownOutCount": 6,
    "VotedCount": 911,
    "OutCount": 411
  },
  {
    "CountyName": "Patrick",
    "TotalMatchedVoters": 877,
    "DemVotedCount": 150,
    "RepVotedCount": 445,
    "UnknownVotedCount": 7,
    "InPersonCount": 447,
    "MailCount": 164,
    "InPersonDem": 77,
    "InPersonRep": 357,
    "MailDem": 73,
    "MailRep": 88,
    "DemOutCount": 106,
    "RepOutCount": 143,
    "UnknownOutCount": 7,
    "VotedCount": 602,
    "OutCount": 256
  },
  {
    "CountyName": "Petersburg (City)",
    "TotalMatchedVoters": 2409,
    "DemVotedCount": 1060,
    "RepVotedCount": 47,
    "UnknownVotedCount": 7,
    "InPersonCount": 565,
    "MailCount": 556,
    "InPersonDem": 527,
    "InPersonRep": 28,
    "MailDem": 533,
    "MailRep": 19,
    "DemOutCount": 1209,
    "RepOutCount": 59,
    "UnknownOutCount": 5,
    "VotedCount": 1114,
    "OutCount": 1273
  },
  {
    "CountyName": "Pittsylvania",
    "TotalMatchedVoters": 3326,
    "DemVotedCount": 737,
    "RepVotedCount": 1407,
    "UnknownVotedCount": 41,
    "InPersonCount": 1564,
    "MailCount": 647,
    "InPersonDem": 424,
    "InPersonRep": 1096,
    "MailDem": 313,
    "MailRep": 311,
    "DemOutCount": 533,
    "RepOutCount": 495,
    "UnknownOutCount": 41,
    "VotedCount": 2185,
    "OutCount": 1069
  },
  {
    "CountyName": "Poquoson (City)",
    "TotalMatchedVoters": 1040,
    "DemVotedCount": 180,
    "RepVotedCount": 546,
    "UnknownVotedCount": 18,
    "InPersonCount": 696,
    "MailCount": 59,
    "InPersonDem": 159,
    "InPersonRep": 511,
    "MailDem": 21,
    "MailRep": 35,
    "DemOutCount": 93,
    "RepOutCount": 174,
    "UnknownOutCount": 4,
    "VotedCount": 744,
    "OutCount": 271
  },
  {
    "CountyName": "Portsmouth (City)",
    "TotalMatchedVoters": 5891,
    "DemVotedCount": 1746,
    "RepVotedCount": 248,
    "UnknownVotedCount": 54,
    "InPersonCount": 1362,
    "MailCount": 704,
    "InPersonDem": 1137,
    "InPersonRep": 182,
    "MailDem": 609,
    "MailRep": 66,
    "DemOutCount": 3120,
    "RepOutCount": 427,
    "UnknownOutCount": 198,
    "VotedCount": 2048,
    "OutCount": 3745
  },
  {
    "CountyName": "Powhatan",
    "TotalMatchedVoters": 2528,
    "DemVotedCount": 546,
    "RepVotedCount": 1335,
    "UnknownVotedCount": 18,
    "InPersonCount": 1539,
    "MailCount": 384,
    "InPersonDem": 352,
    "InPersonRep": 1158,
    "MailDem": 193,
    "MailRep": 177,
    "DemOutCount": 254,
    "RepOutCount": 299,
    "UnknownOutCount": 16,
    "VotedCount": 1899,
    "OutCount": 569
  },
  {
    "CountyName": "Prince Edward",
    "TotalMatchedVoters": 1310,
    "DemVotedCount": 450,
    "RepVotedCount": 305,
    "UnknownVotedCount": 32,
    "InPersonCount": 600,
    "MailCount": 196,
    "InPersonDem": 317,
    "InPersonRep": 248,
    "MailDem": 133,
    "MailRep": 57,
    "DemOutCount": 324,
    "RepOutCount": 139,
    "UnknownOutCount": 31,
    "VotedCount": 787,
    "OutCount": 494
  },
  {
    "CountyName": "Prince George",
    "TotalMatchedVoters": 2255,
    "DemVotedCount": 619,
    "RepVotedCount": 766,
    "UnknownVotedCount": 30,
    "InPersonCount": 1151,
    "MailCount": 277,
    "InPersonDem": 465,
    "InPersonRep": 656,
    "MailDem": 154,
    "MailRep": 110,
    "DemOutCount": 438,
    "RepOutCount": 305,
    "UnknownOutCount": 55,
    "VotedCount": 1415,
    "OutCount": 798
  },
  {
    "CountyName": "Prince William",
    "TotalMatchedVoters": 28328,
    "DemVotedCount": 3371,
    "RepVotedCount": 1798,
    "UnknownVotedCount": 306,
    "InPersonCount": 2354,
    "MailCount": 3172,
    "InPersonDem": 1244,
    "InPersonRep": 979,
    "MailDem": 2127,
    "MailRep": 819,
    "DemOutCount": 15673,
    "RepOutCount": 4424,
    "UnknownOutCount": 2064,
    "VotedCount": 5475,
    "OutCount": 22161
  },
  {
    "CountyName": "Pulaski",
    "TotalMatchedVoters": 2104,
    "DemVotedCount": 508,
    "RepVotedCount": 797,
    "UnknownVotedCount": 32,
    "InPersonCount": 909,
    "MailCount": 437,
    "InPersonDem": 272,
    "InPersonRep": 614,
    "MailDem": 236,
    "MailRep": 183,
    "DemOutCount": 368,
    "RepOutCount": 360,
    "UnknownOutCount": 16,
    "VotedCount": 1337,
    "OutCount": 744
  },
  {
    "CountyName": "Radford (City)",
    "TotalMatchedVoters": 854,
    "DemVotedCount": 316,
    "RepVotedCount": 255,
    "UnknownVotedCount": 47,
    "InPersonCount": 482,
    "MailCount": 141,
    "InPersonDem": 217,
    "InPersonRep": 231,
    "MailDem": 99,
    "MailRep": 24,
    "DemOutCount": 132,
    "RepOutCount": 52,
    "UnknownOutCount": 43,
    "VotedCount": 618,
    "OutCount": 227
  },
  {
    "CountyName": "Rappahannock",
    "TotalMatchedVoters": 736,
    "DemVotedCount": 285,
    "RepVotedCount": 219,
    "UnknownVotedCount": 12,
    "InPersonCount": 357,
    "MailCount": 163,
    "InPersonDem": 168,
    "InPersonRep": 175,
    "MailDem": 117,
    "MailRep": 44,
    "DemOutCount": 131,
    "RepOutCount": 65,
    "UnknownOutCount": 7,
    "VotedCount": 516,
    "OutCount": 203
  },
  {
    "CountyName": "Richmond",
    "TotalMatchedVoters": 310,
    "DemVotedCount": 64,
    "RepVotedCount": 133,
    "UnknownVotedCount": 7,
    "InPersonCount": 207,
    "MailCount": 0,
    "InPersonDem": 64,
    "InPersonRep": 133,
    "MailDem": 0,
    "MailRep": 0,
    "DemOutCount": 39,
    "RepOutCount": 50,
    "UnknownOutCount": 9,
    "VotedCount": 204,
    "OutCount": 98
  },
  {
    "CountyName": "Richmond (City)",
    "TotalMatchedVoters": 12135,
    "DemVotedCount": 3224,
    "RepVotedCount": 428,
    "UnknownVotedCount": 26,
    "InPersonCount": 2455,
    "MailCount": 1247,
    "InPersonDem": 2109,
    "InPersonRep": 317,
    "MailDem": 1115,
    "MailRep": 111,
    "DemOutCount": 7476,
    "RepOutCount": 563,
    "UnknownOutCount": 98,
    "VotedCount": 3678,
    "OutCount": 8137
  },
  {
    "CountyName": "Roanoke",
    "TotalMatchedVoters": 7495,
    "DemVotedCount": 2096,
    "RepVotedCount": 2336,
    "UnknownVotedCount": 152,
    "InPersonCount": 3228,
    "MailCount": 1407,
    "InPersonDem": 1287,
    "InPersonRep": 1819,
    "MailDem": 809,
    "MailRep": 517,
    "DemOutCount": 1406,
    "RepOutCount": 1126,
    "UnknownOutCount": 231,
    "VotedCount": 4584,
    "OutCount": 2763
  },
  {
    "CountyName": "Roanoke (City)",
    "TotalMatchedVoters": 6230,
    "DemVotedCount": 2531,
    "RepVotedCount": 862,
    "UnknownVotedCount": 162,
    "InPersonCount": 2253,
    "MailCount": 1339,
    "InPersonDem": 1559,
    "InPersonRep": 579,
    "MailDem": 971,
    "MailRep": 283,
    "DemOutCount": 1791,
    "RepOutCount": 486,
    "UnknownOutCount": 275,
    "VotedCount": 3555,
    "OutCount": 2552
  },
  {
    "CountyName": "Rockbridge",
    "TotalMatchedVoters": 1698,
    "DemVotedCount": 535,
    "RepVotedCount": 660,
    "UnknownVotedCount": 15,
    "InPersonCount": 1075,
    "MailCount": 152,
    "InPersonDem": 436,
    "InPersonRep": 613,
    "MailDem": 99,
    "MailRep": 47,
    "DemOutCount": 241,
    "RepOutCount": 184,
    "UnknownOutCount": 19,
    "VotedCount": 1210,
    "OutCount": 444
  },
  {
    "CountyName": "Rockingham",
    "TotalMatchedVoters": 4855,
    "DemVotedCount": 1139,
    "RepVotedCount": 2182,
    "UnknownVotedCount": 83,
    "InPersonCount": 2597,
    "MailCount": 844,
    "InPersonDem": 740,
    "InPersonRep": 1771,
    "MailDem": 399,
    "MailRep": 411,
    "DemOutCount": 606,
    "RepOutCount": 664,
    "UnknownOutCount": 85,
    "VotedCount": 3404,
    "OutCount": 1355
  },
  {
    "CountyName": "Russell",
    "TotalMatchedVoters": 988,
    "DemVotedCount": 121,
    "RepVotedCount": 327,
    "UnknownVotedCount": 1,
    "InPersonCount": 450,
    "MailCount": 15,
    "InPersonDem": 114,
    "InPersonRep": 320,
    "MailDem": 7,
    "MailRep": 7,
    "DemOutCount": 236,
    "RepOutCount": 254,
    "UnknownOutCount": 6,
    "VotedCount": 449,
    "OutCount": 496
  },
  {
    "CountyName": "Salem (City)",
    "TotalMatchedVoters": 1815,
    "DemVotedCount": 585,
    "RepVotedCount": 618,
    "UnknownVotedCount": 76,
    "InPersonCount": 925,
    "MailCount": 362,
    "InPersonDem": 373,
    "InPersonRep": 495,
    "MailDem": 212,
    "MailRep": 123,
    "DemOutCount": 237,
    "RepOutCount": 210,
    "UnknownOutCount": 57,
    "VotedCount": 1279,
    "OutCount": 504
  },
  {
    "CountyName": "Scott",
    "TotalMatchedVoters": 1240,
    "DemVotedCount": 116,
    "RepVotedCount": 809,
    "UnknownVotedCount": 8,
    "InPersonCount": 847,
    "MailCount": 109,
    "InPersonDem": 79,
    "InPersonRep": 739,
    "MailDem": 37,
    "MailRep": 70,
    "DemOutCount": 74,
    "RepOutCount": 195,
    "UnknownOutCount": 0,
    "VotedCount": 933,
    "OutCount": 269
  },
  {
    "CountyName": "Shenandoah",
    "TotalMatchedVoters": 2886,
    "DemVotedCount": 796,
    "RepVotedCount": 1279,
    "UnknownVotedCount": 34,
    "InPersonCount": 1766,
    "MailCount": 376,
    "InPersonDem": 604,
    "InPersonRep": 1111,
    "MailDem": 192,
    "MailRep": 168,
    "DemOutCount": 309,
    "RepOutCount": 368,
    "UnknownOutCount": 32,
    "VotedCount": 2109,
    "OutCount": 709
  },
  {
    "CountyName": "Smyth",
    "TotalMatchedVoters": 1027,
    "DemVotedCount": 166,
    "RepVotedCount": 364,
    "UnknownVotedCount": 3,
    "InPersonCount": 301,
    "MailCount": 241,
    "InPersonDem": 67,
    "InPersonRep": 228,
    "MailDem": 99,
    "MailRep": 136,
    "DemOutCount": 135,
    "RepOutCount": 313,
    "UnknownOutCount": 9,
    "VotedCount": 533,
    "OutCount": 457
  },
  {
    "CountyName": "Southampton",
    "TotalMatchedVoters": 1008,
    "DemVotedCount": 271,
    "RepVotedCount": 299,
    "UnknownVotedCount": 11,
    "InPersonCount": 450,
    "MailCount": 138,
    "InPersonDem": 194,
    "InPersonRep": 243,
    "MailDem": 77,
    "MailRep": 56,
    "DemOutCount": 235,
    "RepOutCount": 144,
    "UnknownOutCount": 29,
    "VotedCount": 581,
    "OutCount": 408
  },
  {
    "CountyName": "Spotsylvania",
    "TotalMatchedVoters": 10958,
    "DemVotedCount": 2951,
    "RepVotedCount": 2628,
    "UnknownVotedCount": 249,
    "InPersonCount": 3993,
    "MailCount": 1882,
    "InPersonDem": 1753,
    "InPersonRep": 2069,
    "MailDem": 1198,
    "MailRep": 559,
    "DemOutCount": 2930,
    "RepOutCount": 1372,
    "UnknownOutCount": 573,
    "VotedCount": 5828,
    "OutCount": 4875
  },
  {
    "CountyName": "Stafford",
    "TotalMatchedVoters": 10503,
    "DemVotedCount": 2378,
    "RepVotedCount": 1861,
    "UnknownVotedCount": 234,
    "InPersonCount": 3030,
    "MailCount": 1490,
    "InPersonDem": 1455,
    "InPersonRep": 1408,
    "MailDem": 923,
    "MailRep": 453,
    "DemOutCount": 3489,
    "RepOutCount": 1616,
    "UnknownOutCount": 661,
    "VotedCount": 4473,
    "OutCount": 5766
  },
  {
    "CountyName": "Staunton (City)",
    "TotalMatchedVoters": 2190,
    "DemVotedCount": 896,
    "RepVotedCount": 378,
    "UnknownVotedCount": 107,
    "InPersonCount": 1022,
    "MailCount": 380,
    "InPersonDem": 645,
    "InPersonRep": 276,
    "MailDem": 251,
    "MailRep": 102,
    "DemOutCount": 489,
    "RepOutCount": 164,
    "UnknownOutCount": 101,
    "VotedCount": 1381,
    "OutCount": 754
  },
  {
    "CountyName": "Suffolk (City)",
    "TotalMatchedVoters": 7211,
    "DemVotedCount": 1627,
    "RepVotedCount": 792,
    "UnknownVotedCount": 90,
    "InPersonCount": 2199,
    "MailCount": 325,
    "InPersonDem": 1400,
    "InPersonRep": 718,
    "MailDem": 227,
    "MailRep": 74,
    "DemOutCount": 3188,
    "RepOutCount": 1039,
    "UnknownOutCount": 345,
    "VotedCount": 2509,
    "OutCount": 4572
  },
  {
    "CountyName": "Surry",
    "TotalMatchedVoters": 580,
    "DemVotedCount": 200,
    "RepVotedCount": 111,
    "UnknownVotedCount": 4,
    "InPersonCount": 215,
    "MailCount": 101,
    "InPersonDem": 130,
    "InPersonRep": 82,
    "MailDem": 70,
    "MailRep": 29,
    "DemOutCount": 188,
    "RepOutCount": 59,
    "UnknownOutCount": 9,
    "VotedCount": 315,
    "OutCount": 256
  },
  {
    "CountyName": "Sussex",
    "TotalMatchedVoters": 442,
    "DemVotedCount": 101,
    "RepVotedCount": 121,
    "UnknownVotedCount": 9,
    "InPersonCount": 170,
    "MailCount": 61,
    "InPersonDem": 68,
    "InPersonRep": 95,
    "MailDem": 33,
    "MailRep": 26,
    "DemOutCount": 159,
    "RepOutCount": 36,
    "UnknownOutCount": 10,
    "VotedCount": 231,
    "OutCount": 205
  },
  {
    "CountyName": "Tazewell",
    "TotalMatchedVoters": 1934,
    "DemVotedCount": 336,
    "RepVotedCount": 1009,
    "UnknownVotedCount": 9,
    "InPersonCount": 1109,
    "MailCount": 276,
    "InPersonDem": 205,
    "InPersonRep": 870,
    "MailDem": 131,
    "MailRep": 139,
    "DemOutCount": 193,
    "RepOutCount": 333,
    "UnknownOutCount": 4,
    "VotedCount": 1354,
    "OutCount": 530
  },
  {
    "CountyName": "Virginia Beach (City)",
    "TotalMatchedVoters": 35992,
    "DemVotedCount": 5562,
    "RepVotedCount": 4792,
    "UnknownVotedCount": 493,
    "InPersonCount": 8662,
    "MailCount": 2298,
    "InPersonDem": 4181,
    "InPersonRep": 4047,
    "MailDem": 1381,
    "MailRep": 744,
    "DemOutCount": 14992,
    "RepOutCount": 6954,
    "UnknownOutCount": 2419,
    "VotedCount": 10847,
    "OutCount": 24365
  },
  {
    "CountyName": "Warren",
    "TotalMatchedVoters": 2750,
    "DemVotedCount": 774,
    "RepVotedCount": 1055,
    "UnknownVotedCount": 25,
    "InPersonCount": 1431,
    "MailCount": 446,
    "InPersonDem": 521,
    "InPersonRep": 873,
    "MailDem": 253,
    "MailRep": 182,
    "DemOutCount": 425,
    "RepOutCount": 386,
    "UnknownOutCount": 25,
    "VotedCount": 1854,
    "OutCount": 836
  },
  {
    "CountyName": "Washington",
    "TotalMatchedVoters": 2956,
    "DemVotedCount": 583,
    "RepVotedCount": 1216,
    "UnknownVotedCount": 20,
    "InPersonCount": 1441,
    "MailCount": 396,
    "InPersonDem": 375,
    "InPersonRep": 1039,
    "MailDem": 208,
    "MailRep": 177,
    "DemOutCount": 481,
    "RepOutCount": 574,
    "UnknownOutCount": 24,
    "VotedCount": 1819,
    "OutCount": 1079
  },
  {
    "CountyName": "Waynesboro (City)",
    "TotalMatchedVoters": 1690,
    "DemVotedCount": 513,
    "RepVotedCount": 437,
    "UnknownVotedCount": 85,
    "InPersonCount": 757,
    "MailCount": 291,
    "InPersonDem": 337,
    "InPersonRep": 347,
    "MailDem": 176,
    "MailRep": 90,
    "DemOutCount": 347,
    "RepOutCount": 173,
    "UnknownOutCount": 101,
    "VotedCount": 1035,
    "OutCount": 621
  },
  {
    "CountyName": "Westmoreland",
    "TotalMatchedVoters": 1350,
    "DemVotedCount": 407,
    "RepVotedCount": 415,
    "UnknownVotedCount": 27,
    "InPersonCount": 692,
    "MailCount": 168,
    "InPersonDem": 304,
    "InPersonRep": 361,
    "MailDem": 103,
    "MailRep": 54,
    "DemOutCount": 274,
    "RepOutCount": 158,
    "UnknownOutCount": 33,
    "VotedCount": 849,
    "OutCount": 465
  },
  {
    "CountyName": "Williamsburg (City)",
    "TotalMatchedVoters": 1477,
    "DemVotedCount": 719,
    "RepVotedCount": 297,
    "UnknownVotedCount": 16,
    "InPersonCount": 802,
    "MailCount": 232,
    "InPersonDem": 543,
    "InPersonRep": 246,
    "MailDem": 176,
    "MailRep": 51,
    "DemOutCount": 354,
    "RepOutCount": 73,
    "UnknownOutCount": 1,
    "VotedCount": 1032,
    "OutCount": 428
  },
  {
    "CountyName": "Winchester (City)",
    "TotalMatchedVoters": 1560,
    "DemVotedCount": 620,
    "RepVotedCount": 387,
    "UnknownVotedCount": 55,
    "InPersonCount": 859,
    "MailCount": 216,
    "InPersonDem": 490,
    "InPersonRep": 327,
    "MailDem": 130,
    "MailRep": 60,
    "DemOutCount": 315,
    "RepOutCount": 86,
    "UnknownOutCount": 61,
    "VotedCount": 1062,
    "OutCount": 462
  },
  {
    "CountyName": "Wise",
    "TotalMatchedVoters": 1259,
    "DemVotedCount": 175,
    "RepVotedCount": 489,
    "UnknownVotedCount": 10,
    "InPersonCount": 419,
    "MailCount": 271,
    "InPersonDem": 70,
    "InPersonRep": 328,
    "MailDem": 105,
    "MailRep": 161,
    "DemOutCount": 195,
    "RepOutCount": 347,
    "UnknownOutCount": 7,
    "VotedCount": 674,
    "OutCount": 549
  },
  {
    "CountyName": "Wythe",
    "TotalMatchedVoters": 1420,
    "DemVotedCount": 250,
    "RepVotedCount": 537,
    "UnknownVotedCount": 6,
    "InPersonCount": 730,
    "MailCount": 75,
    "InPersonDem": 214,
    "InPersonRep": 499,
    "MailDem": 36,
    "MailRep": 38,
    "DemOutCount": 216,
    "RepOutCount": 368,
    "UnknownOutCount": 12,
    "VotedCount": 793,
    "OutCount": 596
  },
  {
    "CountyName": "York",
    "TotalMatchedVoters": 7128,
    "DemVotedCount": 2289,
    "RepVotedCount": 2526,
    "UnknownVotedCount": 236,
    "InPersonCount": 4056,
    "MailCount": 1040,
    "InPersonDem": 1661,
    "InPersonRep": 2188,
    "MailDem": 628,
    "MailRep": 338,
    "DemOutCount": 1119,
    "RepOutCount": 586,
    "UnknownOutCount": 235,
    "VotedCount": 5051,
    "OutCount": 1940
  }
]