[
  {
    "ReturnDate": "2026-03-06",
    "DayOfWeek": "Friday",
    "TotalReturned": 27152,
    "InPersonTotal": 27036,
    "InPersonDem": 13757,
    "InPersonRep": 13112,
    "InPersonUnknown": 167,
    "MailTotal": 116,
    "MailDem": 95,
    "MailRep": 20,
    "MailUnknown": 1,
    "CumTotalReturned": 27152,
    "CumInPersonTotal": 27036,
    "CumMailTotal": 116,
    "CumInPersonDem": 13757,
    "CumInPersonRep": 13112,
    "CumInPersonUnknown": 167,
    "CumMailDem": 95,
    "CumMailRep": 20,
    "CumMailUnknown": 1
  },
  {
    "ReturnDate": "2026-03-07",
    "DayOfWeek": "Saturday",
    "TotalReturned": 440,
    "InPersonTotal": 440,
    "InPersonDem": 187,
    "InPersonRep": 248,
    "InPersonUnknown": 5,
    "MailTotal": 0,
    "MailDem": 0,
    "MailRep": 0,
    "MailUnknown": 0,
    "CumTotalReturned": 27592,
    "CumInPersonTotal": 27476,
    "CumMailTotal": 116,
    "CumInPersonDem": 13944,
    "CumInPersonRep": 13360,
    "CumInPersonUnknown": 172,
    "CumMailDem": 95,
    "CumMailRep": 20,
    "CumMailUnknown": 1
  },
  {
    "ReturnDate": "2026-03-08",
    "DayOfWeek": "Sunday",
    "TotalReturned": 147,
    "InPersonTotal": 145,
    "InPersonDem": 102,
    "InPersonRep": 43,
    "InPersonUnknown": 0,
    "MailTotal": 2,
    "MailDem": 1,
    "MailRep": 1,
    "MailUnknown": 0,
    "CumTotalReturned": 27739,
    "CumInPersonTotal": 27621,
    "CumMailTotal": 118,
    "CumInPersonDem": 14046,
    "CumInPersonRep": 13403,
    "CumInPersonUnknown": 172,
    "CumMailDem": 96,
    "CumMailRep": 21,
    "CumMailUnknown": 1
  },
  {
    "ReturnDate": "2026-03-09",
    "DayOfWeek": "Monday",
    "TotalReturned": 23298,
    "InPersonTotal": 22872,
    "InPersonDem": 11573,
    "InPersonRep": 11117,
    "InPersonUnknown": 182,
    "MailTotal": 426,
    "MailDem": 306,
    "MailRep": 119,
    "MailUnknown": 1,
    "CumTotalReturned": 51037,
    "CumInPersonTotal": 50493,
    "CumMailTotal": 544,
    "CumInPersonDem": 25619,
    "CumInPersonRep": 24520,
    "CumInPersonUnknown": 354,
    "CumMailDem": 402,
    "CumMailRep": 140,
    "CumMailUnknown": 2
  },
  {
    "ReturnDate": "2026-03-10",
    "DayOfWeek": "Tuesday",
    "TotalReturned": 23690,
    "InPersonTotal": 22175,
    "InPersonDem": 11236,
    "InPersonRep": 10792,
    "InPersonUnknown": 147,
    "MailTotal": 1515,
    "MailDem": 1133,
    "MailRep": 377,
    "MailUnknown": 5,
    "CumTotalReturned": 74727,
    "CumInPersonTotal": 72668,
    "CumMailTotal": 2059,
    "CumInPersonDem": 36855,
    "CumInPersonRep": 35312,
    "CumInPersonUnknown": 501,
    "CumMailDem": 1535,
    "CumMailRep": 517,
    "CumMailUnknown": 7
  },
  {
    "ReturnDate": "2026-03-11",
    "DayOfWeek": "Wednesday",
    "TotalReturned": 23535,
    "InPersonTotal": 20745,
    "InPersonDem": 10221,
    "InPersonRep": 10358,
    "InPersonUnknown": 166,
    "MailTotal": 2790,
    "MailDem": 1988,
    "MailRep": 785,
    "MailUnknown": 17,
    "CumTotalReturned": 98262,
    "CumInPersonTotal": 93413,
    "CumMailTotal": 4849,
    "CumInPersonDem": 47076,
    "CumInPersonRep": 45670,
    "CumInPersonUnknown": 667,
    "CumMailDem": 3523,
    "CumMailRep": 1302,
    "CumMailUnknown": 24
  },
  {
    "ReturnDate": "2026-03-12",
    "DayOfWeek": "Thursday",
    "TotalReturned": 21269,
    "InPersonTotal": 13237,
    "InPersonDem": 6219,
    "InPersonRep": 6891,
    "InPersonUnknown": 127,
    "MailTotal": 8032,
    "MailDem": 5819,
    "MailRep": 2172,
    "MailUnknown": 41,
    "CumTotalReturned": 119531,
    "CumInPersonTotal": 106650,
    "CumMailTotal": 12881,
    "CumInPersonDem": 53295,
    "CumInPersonRep": 52561,
    "CumInPersonUnknown": 794,
    "CumMailDem": 9342,
    "CumMailRep": 3474,
    "CumMailUnknown": 65
  },
  {
    "ReturnDate": "2026-03-13",
    "DayOfWeek": "Friday",
    "TotalReturned": 42758,
    "InPersonTotal": 27307,
    "InPersonDem": 13761,
    "InPersonRep": 13317,
    "InPersonUnknown": 229,
    "MailTotal": 15451,
    "MailDem": 11088,
    "MailRep": 4272,
    "MailUnknown": 91,
    "CumTotalReturned": 162289,
    "CumInPersonTotal": 133957,
    "CumMailTotal": 28332,
    "CumInPersonDem": 67056,
    "CumInPersonRep": 65878,
    "CumInPersonUnknown": 1023,
    "CumMailDem": 20430,
    "CumMailRep": 7746,
    "CumMailUnknown": 156
  },
  {
    "ReturnDate": "2026-03-14",
    "DayOfWeek": "Saturday",
    "TotalReturned": 4095,
    "InPersonTotal": 961,
    "InPersonDem": 433,
    "InPersonRep": 520,
    "InPersonUnknown": 8,
    "MailTotal": 3134,
    "MailDem": 2585,
    "MailRep": 528,
    "MailUnknown": 21,
    "CumTotalReturned": 166384,
    "CumInPersonTotal": 134918,
    "CumMailTotal": 31466,
    "CumInPersonDem": 67489,
    "CumInPersonRep": 66398,
    "CumInPersonUnknown": 1031,
    "CumMailDem": 23015,
    "CumMailRep": 8274,
    "CumMailUnknown": 177
  },
  {
    "ReturnDate": "2026-03-15",
    "DayOfWeek": "Sunday",
    "TotalReturned": 104,
    "InPersonTotal": 0,
    "InPersonDem": 0,
    "InPersonRep": 0,
    "InPersonUnknown": 0,
    "MailTotal": 104,
    "MailDem": 98,
    "MailRep": 6,
    "MailUnknown": 0,
    "CumTotalReturned": 166488,
    "CumInPersonTotal": 134918,
    "CumMailTotal": 31570,
    "CumInPersonDem": 67489,
    "CumInPersonRep": 66398,
    "CumInPersonUnknown": 1031,
    "CumMailDem": 23113,
    "CumMailRep": 8280,
    "CumMailUnknown": 177
  },
  {
    "ReturnDate": "2026-03-16",
    "DayOfWeek": "Monday",
    "TotalReturned": 37255,
    "InPersonTotal": 10980,
    "InPersonDem": 5284,
    "InPersonRep": 5591,
    "InPersonUnknown": 105,
    "MailTotal": 26275,
    "MailDem": 18661,
    "MailRep": 7452,
    "MailUnknown": 162,
    "CumTotalReturned": 203743,
    "CumInPersonTotal": 145898,
    "CumMailTotal": 57845,
    "CumInPersonDem": 72773,
    "CumInPersonRep": 71989,
    "CumInPersonUnknown": 1136,
    "CumMailDem": 41774,
    "CumMailRep": 15732,
    "CumMailUnknown": 339
  },
  {
    "ReturnDate": "2026-03-17",
    "DayOfWeek": "Tuesday",
    "TotalReturned": 40619,
    "InPersonTotal": 23151,
    "InPersonDem": 12130,
    "InPersonRep": 10845,
    "InPersonUnknown": 176,
    "MailTotal": 17468,
    "MailDem": 12070,
    "MailRep": 5292,
    "MailUnknown": 106,
    "CumTotalReturned": 244362,
    "CumInPersonTotal": 169049,
    "CumMailTotal": 75313,
    "CumInPersonDem": 84903,
    "CumInPersonRep": 82834,
    "CumInPersonUnknown": 1312,
    "CumMailDem": 53844,
    "CumMailRep": 21024,
    "CumMailUnknown": 445
  },
  {
    "ReturnDate": "2026-03-18",
    "DayOfWeek": "Wednesday",
    "TotalReturned": 40371,
    "InPersonTotal": 23167,
    "InPersonDem": 11653,
    "InPersonRep": 11310,
    "InPersonUnknown": 204,
    "MailTotal": 17204,
    "MailDem": 12423,
    "MailRep": 4687,
    "MailUnknown": 94,
    "CumTotalReturned": 284733,
    "CumInPersonTotal": 192216,
    "CumMailTotal": 92517,
    "CumInPersonDem": 96556,
    "CumInPersonRep": 94144,
    "CumInPersonUnknown": 1516,
    "CumMailDem": 66267,
    "CumMailRep": 25711,
    "CumMailUnknown": 539
  },
  {
    "ReturnDate": "2026-03-19",
    "DayOfWeek": "Thursday",
    "TotalReturned": 39101,
    "InPersonTotal": 23049,
    "InPersonDem": 11843,
    "InPersonRep": 11004,
    "InPersonUnknown": 202,
    "MailTotal": 16052,
    "MailDem": 11336,
    "MailRep": 4607,
    "MailUnknown": 109,
    "CumTotalReturned": 323834,
    "CumInPersonTotal": 215265,
    "CumMailTotal": 108569,
    "CumInPersonDem": 108399,
    "CumInPersonRep": 105148,
    "CumInPersonUnknown": 1718,
    "CumMailDem": 77603,
    "CumMailRep": 30318,
    "CumMailUnknown": 648
  },
  {
    "ReturnDate": "2026-03-20",
    "DayOfWeek": "Friday",
    "TotalReturned": 41911,
    "InPersonTotal": 28683,
    "InPersonDem": 15276,
    "InPersonRep": 13124,
    "InPersonUnknown": 283,
    "MailTotal": 13228,
    "MailDem": 9563,
    "MailRep": 3573,
    "MailUnknown": 92,
    "CumTotalReturned": 365745,
    "CumInPersonTotal": 243948,
    "CumMailTotal": 121797,
    "CumInPersonDem": 123675,
    "CumInPersonRep": 118272,
    "CumInPersonUnknown": 2001,
    "CumMailDem": 87166,
    "CumMailRep": 33891,
    "CumMailUnknown": 740
  },
  {
    "ReturnDate": "2026-03-21",
    "DayOfWeek": "Saturday",
    "TotalReturned": 99,
    "InPersonTotal": 0,
    "InPersonDem": 0,
    "InPersonRep": 0,
    "InPersonUnknown": 0,
    "MailTotal": 99,
    "MailDem": 90,
    "MailRep": 5,
    "MailUnknown": 4,
    "CumTotalReturned": 365844,
    "CumInPersonTotal": 243948,
    "CumMailTotal": 121896,
    "CumInPersonDem": 123675,
    "CumInPersonRep": 118272,
    "CumInPersonUnknown": 2001,
    "CumMailDem": 87256,
    "CumMailRep": 33896,
    "CumMailUnknown": 744
  },
  {
    "ReturnDate": "2026-03-22",
    "DayOfWeek": "Sunday",
    "TotalReturned": 194,
    "InPersonTotal": 0,
    "InPersonDem": 0,
    "InPersonRep": 0,
    "InPersonUnknown": 0,
    "MailTotal": 194,
    "MailDem": 163,
    "MailRep": 31,
    "MailUnknown": 0,
    "CumTotalReturned": 366038,
    "CumInPersonTotal": 243948,
    "CumMailTotal": 122090,
    "CumInPersonDem": 123675,
    "CumInPersonRep": 118272,
    "CumInPersonUnknown": 2001,
    "CumMailDem": 87419,
    "CumMailRep": 33927,
    "CumMailUnknown": 744
  },
  {
    "ReturnDate": "2026-03-23",
    "DayOfWeek": "Monday",
    "TotalReturned": 50441,
    "InPersonTotal": 21614,
    "InPersonDem": 11224,
    "InPersonRep": 10151,
    "InPersonUnknown": 239,
    "MailTotal": 28827,
    "MailDem": 20563,
    "MailRep": 8059,
    "MailUnknown": 205,
    "CumTotalReturned": 416479,
    "CumInPersonTotal": 265562,
    "CumMailTotal": 150917,
    "CumInPersonDem": 134899,
    "CumInPersonRep": 128423,
    "CumInPersonUnknown": 2240,
    "CumMailDem": 107982,
    "CumMailRep": 41986,
    "CumMailUnknown": 949
  },
  {
    "ReturnDate": "2026-03-24",
    "DayOfWeek": "Tuesday",
    "TotalReturned": 32463,
    "InPersonTotal": 22014,
    "InPersonDem": 11034,
    "InPersonRep": 10737,
    "InPersonUnknown": 243,
    "MailTotal": 10449,
    "MailDem": 7579,
    "MailRep": 2791,
    "MailUnknown": 79,
    "CumTotalReturned": 448942,
    "CumInPersonTotal": 287576,
    "CumMailTotal": 161366,
    "CumInPersonDem": 145933,
    "CumInPersonRep": 139160,
    "CumInPersonUnknown": 2483,
    "CumMailDem": 115561,
    "CumMailRep": 44777,
    "CumMailUnknown": 1028
  },
  {
    "ReturnDate": "2026-03-25",
    "DayOfWeek": "Wednesday",
    "TotalReturned": 28689,
    "InPersonTotal": 19954,
    "InPersonDem": 10258,
    "InPersonRep": 9512,
    "InPersonUnknown": 184,
    "MailTotal": 8735,
    "MailDem": 6618,
    "MailRep": 2031,
    "MailUnknown": 86,
    "CumTotalReturned": 477631,
    "CumInPersonTotal": 307530,
    "CumMailTotal": 170101,
    "CumInPersonDem": 156191,
    "CumInPersonRep": 148672,
    "CumInPersonUnknown": 2667,
    "CumMailDem": 122179,
    "CumMailRep": 46808,
    "CumMailUnknown": 1114
  },
  {
    "ReturnDate": "2026-03-26",
    "DayOfWeek": "Thursday",
    "TotalReturned": 28886,
    "InPersonTotal": 19305,
    "InPersonDem": 9732,
    "InPersonRep": 9362,
    "InPersonUnknown": 211,
    "MailTotal": 9581,
    "MailDem": 6879,
    "MailRep": 2609,
    "MailUnknown": 93,
    "CumTotalReturned": 506517,
    "CumInPersonTotal": 326835,
    "CumMailTotal": 179682,
    "CumInPersonDem": 165923,
    "CumInPersonRep": 158034,
    "CumInPersonUnknown": 2878,
    "CumMailDem": 129058,
    "CumMailRep": 49417,
    "CumMailUnknown": 1207
  },
  {
    "ReturnDate": "2026-03-27",
    "DayOfWeek": "Friday",
    "TotalReturned": 31665,
    "InPersonTotal": 22994,
    "InPersonDem": 11862,
    "InPersonRep": 10875,
    "InPersonUnknown": 257,
    "MailTotal": 8671,
    "MailDem": 6320,
    "MailRep": 2284,
    "MailUnknown": 67,
    "CumTotalReturned": 538182,
    "CumInPersonTotal": 349829,
    "CumMailTotal": 188353,
    "CumInPersonDem": 177785,
    "CumInPersonRep": 168909,
    "CumInPersonUnknown": 3135,
    "CumMailDem": 135378,
    "CumMailRep": 51701,
    "CumMailUnknown": 1274
  },
  {
    "ReturnDate": "2026-03-28",
    "DayOfWeek": "Saturday",
    "TotalReturned": 129,
    "InPersonTotal": 2,
    "InPersonDem": 0,
    "InPersonRep": 2,
    "InPersonUnknown": 0,
    "MailTotal": 127,
    "MailDem": 106,
    "MailRep": 20,
    "MailUnknown": 1,
    "CumTotalReturned": 538311,
    "CumInPersonTotal": 349831,
    "CumMailTotal": 188480,
    "CumInPersonDem": 177785,
    "CumInPersonRep": 168911,
    "CumInPersonUnknown": 3135,
    "CumMailDem": 135484,
    "CumMailRep": 51721,
    "CumMailUnknown": 1275
  },
  {
    "ReturnDate": "2026-03-29",
    "DayOfWeek": "Sunday",
    "TotalReturned": 124,
    "InPersonTotal": 0,
    "InPersonDem": 0,
    "InPersonRep": 0,
    "InPersonUnknown": 0,
    "MailTotal": 124,
    "MailDem": 116,
    "MailRep": 7,
    "MailUnknown": 1,
    "CumTotalReturned": 538435,
    "CumInPersonTotal": 349831,
    "CumMailTotal": 188604,
    "CumInPersonDem": 177785,
    "CumInPersonRep": 168911,
    "CumInPersonUnknown": 3135,
    "CumMailDem": 135600,
    "CumMailRep": 51728,
    "CumMailUnknown": 1276
  },
  {
    "ReturnDate": "2026-03-30",
    "DayOfWeek": "Monday",
    "TotalReturned": 34229,
    "InPersonTotal": 21832,
    "InPersonDem": 11480,
    "InPersonRep": 10122,
    "InPersonUnknown": 230,
    "MailTotal": 12397,
    "MailDem": 9117,
    "MailRep": 3166,
    "MailUnknown": 114,
    "CumTotalReturned": 572664,
    "CumInPersonTotal": 371663,
    "CumMailTotal": 201001,
    "CumInPersonDem": 189265,
    "CumInPersonRep": 179033,
    "CumInPersonUnknown": 3365,
    "CumMailDem": 144717,
    "CumMailRep": 54894,
    "CumMailUnknown": 1390
  },
  {
    "ReturnDate": "2026-03-31",
    "DayOfWeek": "Tuesday",
    "TotalReturned": 25349,
    "InPersonTotal": 21354,
    "InPersonDem": 11040,
    "InPersonRep": 10070,
    "InPersonUnknown": 244,
    "MailTotal": 3995,
    "MailDem": 2907,
    "MailRep": 1061,
    "MailUnknown": 27,
    "CumTotalReturned": 598013,
    "CumInPersonTotal": 393017,
    "CumMailTotal": 204996,
    "CumInPersonDem": 200305,
    "CumInPersonRep": 189103,
    "CumInPersonUnknown": 3609,
    "CumMailDem": 147624,
    "CumMailRep": 55955,
    "CumMailUnknown": 1417
  },
  {
    "ReturnDate": "2026-04-01",
    "DayOfWeek": "Wednesday",
    "TotalReturned": 25476,
    "InPersonTotal": 19965,
    "InPersonDem": 9980,
    "InPersonRep": 9747,
    "InPersonUnknown": 238,
    "MailTotal": 5511,
    "MailDem": 4089,
    "MailRep": 1362,
    "MailUnknown": 60,
    "CumTotalReturned": 623489,
    "CumInPersonTotal": 412982,
    "CumMailTotal": 210507,
    "CumInPersonDem": 210285,
    "CumInPersonRep": 198850,
    "CumInPersonUnknown": 3847,
    "CumMailDem": 151713,
    "CumMailRep": 57317,
    "CumMailUnknown": 1477
  },
  {
    "ReturnDate": "2026-04-02",
    "DayOfWeek": "Thursday",
    "TotalReturned": 28659,
    "InPersonTotal": 21102,
    "InPersonDem": 10454,
    "InPersonRep": 10397,
    "InPersonUnknown": 251,
    "MailTotal": 7557,
    "MailDem": 5518,
    "MailRep": 1972,
    "MailUnknown": 67,
    "CumTotalReturned": 652148,
    "CumInPersonTotal": 434084,
    "CumMailTotal": 218064,
    "CumInPersonDem": 220739,
    "CumInPersonRep": 209247,
    "CumInPersonUnknown": 4098,
    "CumMailDem": 157231,
    "CumMailRep": 59289,
    "CumMailUnknown": 1544
  },
  {
    "ReturnDate": "2026-04-03",
    "DayOfWeek": "Friday",
    "TotalReturned": 29728,
    "InPersonTotal": 25371,
    "InPersonDem": 12820,
    "InPersonRep": 12238,
    "InPersonUnknown": 313,
    "MailTotal": 4357,
    "MailDem": 3181,
    "MailRep": 1122,
    "MailUnknown": 54,
    "CumTotalReturned": 681876,
    "CumInPersonTotal": 459455,
    "CumMailTotal": 222421,
    "CumInPersonDem": 233559,
    "CumInPersonRep": 221485,
    "CumInPersonUnknown": 4411,
    "CumMailDem": 160412,
    "CumMailRep": 60411,
    "CumMailUnknown": 1598
  },
  {
    "ReturnDate": "2026-04-04",
    "DayOfWeek": "Saturday",
    "TotalReturned": 91,
    "InPersonTotal": 41,
    "InPersonDem": 23,
    "InPersonRep": 17,
    "InPersonUnknown": 1,
    "MailTotal": 50,
    "MailDem": 45,
    "MailRep": 3,
    "MailUnknown": 2,
    "CumTotalReturned": 681967,
    "CumInPersonTotal": 459496,
    "CumMailTotal": 222471,
    "CumInPersonDem": 233582,
    "CumInPersonRep": 221502,
    "CumInPersonUnknown": 4412,
    "CumMailDem": 160457,
    "CumMailRep": 60414,
    "CumMailUnknown": 1600
  },
  {
    "ReturnDate": "2026-04-05",
    "DayOfWeek": "Sunday",
    "TotalReturned": 44,
    "InPersonTotal": 0,
    "InPersonDem": 0,
    "InPersonRep": 0,
    "InPersonUnknown": 0,
    "MailTotal": 44,
    "MailDem": 39,
    "MailRep": 5,
    "MailUnknown": 0,
    "CumTotalReturned": 682011,
    "CumInPersonTotal": 459496,
    "CumMailTotal": 222515,
    "CumInPersonDem": 233582,
    "CumInPersonRep": 221502,
    "CumInPersonUnknown": 4412,
    "CumMailDem": 160496,
    "CumMailRep": 60419,
    "CumMailUnknown": 1600
  },
  {
    "ReturnDate": "2026-04-06",
    "DayOfWeek": "Monday",
    "TotalReturned": 38191,
    "InPersonTotal": 28483,
    "InPersonDem": 14521,
    "InPersonRep": 13607,
    "InPersonUnknown": 355,
    "MailTotal": 9708,
    "MailDem": 7091,
    "MailRep": 2517,
    "MailUnknown": 100,
    "CumTotalReturned": 720202,
    "CumInPersonTotal": 487979,
    "CumMailTotal": 232223,
    "CumInPersonDem": 248103,
    "CumInPersonRep": 235109,
    "CumInPersonUnknown": 4767,
    "CumMailDem": 167587,
    "CumMailRep": 62936,
    "CumMailUnknown": 1700
  },
  {
    "ReturnDate": "2026-04-07",
    "DayOfWeek": "Tuesday",
    "TotalReturned": 31159,
    "InPersonTotal": 27309,
    "InPersonDem": 13202,
    "InPersonRep": 13741,
    "InPersonUnknown": 366,
    "MailTotal": 3850,
    "MailDem": 2763,
    "MailRep": 1055,
    "MailUnknown": 32,
    "CumTotalReturned": 751361,
    "CumInPersonTotal": 515288,
    "CumMailTotal": 236073,
    "CumInPersonDem": 261305,
    "CumInPersonRep": 248850,
    "CumInPersonUnknown": 5133,
    "CumMailDem": 170350,
    "CumMailRep": 63991,
    "CumMailUnknown": 1732
  },
  {
    "ReturnDate": "2026-04-08",
    "DayOfWeek": "Wednesday",
    "TotalReturned": 30783,
    "InPersonTotal": 26531,
    "InPersonDem": 12707,
    "InPersonRep": 13471,
    "InPersonUnknown": 353,
    "MailTotal": 4252,
    "MailDem": 3117,
    "MailRep": 1077,
    "MailUnknown": 58,
    "CumTotalReturned": 782144,
    "CumInPersonTotal": 541819,
    "CumMailTotal": 240325,
    "CumInPersonDem": 274012,
    "CumInPersonRep": 262321,
    "CumInPersonUnknown": 5486,
    "CumMailDem": 173467,
    "CumMailRep": 65068,
    "CumMailUnknown": 1790
  },
  {
    "ReturnDate": "2026-04-09",
    "DayOfWeek": "Thursday",
    "TotalReturned": 32356,
    "InPersonTotal": 26348,
    "InPersonDem": 12344,
    "InPersonRep": 13626,
    "InPersonUnknown": 378,
    "MailTotal": 6008,
    "MailDem": 4303,
    "MailRep": 1624,
    "MailUnknown": 81,
    "CumTotalReturned": 814500,
    "CumInPersonTotal": 568167,
    "CumMailTotal": 246333,
    "CumInPersonDem": 286356,
    "CumInPersonRep": 275947,
    "CumInPersonUnknown": 5864,
    "CumMailDem": 177770,
    "CumMailRep": 66692,
    "CumMailUnknown": 1871
  },
  {
    "ReturnDate": "2026-04-10",
    "DayOfWeek": "Friday",
    "TotalReturned": 41935,
    "InPersonTotal": 37161,
    "InPersonDem": 17458,
    "InPersonRep": 19128,
    "InPersonUnknown": 575,
    "MailTotal": 4774,
    "MailDem": 3375,
    "MailRep": 1329,
    "MailUnknown": 70,
    "CumTotalReturned": 856435,
    "CumInPersonTotal": 605328,
    "CumMailTotal": 251107,
    "CumInPersonDem": 303814,
    "CumInPersonRep": 295075,
    "CumInPersonUnknown": 6439,
    "CumMailDem": 181145,
    "CumMailRep": 68021,
    "CumMailUnknown": 1941
  },
  {
    "ReturnDate": "2026-04-11",
    "DayOfWeek": "Saturday",
    "TotalReturned": 68026,
    "InPersonTotal": 65530,
    "InPersonDem": 40955,
    "InPersonRep": 23726,
    "InPersonUnknown": 849,
    "MailTotal": 2496,
    "MailDem": 1870,
    "MailRep": 593,
    "MailUnknown": 33,
    "CumTotalReturned": 924461,
    "CumInPersonTotal": 670858,
    "CumMailTotal": 253603,
    "CumInPersonDem": 344769,
    "CumInPersonRep": 318801,
    "CumInPersonUnknown": 7288,
    "CumMailDem": 183015,
    "CumMailRep": 68614,
    "CumMailUnknown": 1974
  },
  {
    "ReturnDate": "2026-04-12",
    "DayOfWeek": "Sunday",
    "TotalReturned": 5081,
    "InPersonTotal": 4973,
    "InPersonDem": 3302,
    "InPersonRep": 1614,
    "InPersonUnknown": 57,
    "MailTotal": 108,
    "MailDem": 98,
    "MailRep": 9,
    "MailUnknown": 1,
    "CumTotalReturned": 929542,
    "CumInPersonTotal": 675831,
    "CumMailTotal": 253711,
    "CumInPersonDem": 348071,
    "CumInPersonRep": 320415,
    "CumInPersonUnknown": 7345,
    "CumMailDem": 183113,
    "CumMailRep": 68623,
    "CumMailUnknown": 1975
  },
  {
    "ReturnDate": "2026-04-13",
    "DayOfWeek": "Monday",
    "TotalReturned": 58766,
    "InPersonTotal": 51204,
    "InPersonDem": 26183,
    "InPersonRep": 24332,
    "InPersonUnknown": 689,
    "MailTotal": 7562,
    "MailDem": 5428,
    "MailRep": 2028,
    "MailUnknown": 106,
    "CumTotalReturned": 988308,
    "CumInPersonTotal": 727035,
    "CumMailTotal": 261273,
    "CumInPersonDem": 374254,
    "CumInPersonRep": 344747,
    "CumInPersonUnknown": 8034,
    "CumMailDem": 188541,
    "CumMailRep": 70651,
    "CumMailUnknown": 2081
  },
  {
    "ReturnDate": "2026-04-14",
    "DayOfWeek": "Tuesday",
    "TotalReturned": 58407,
    "InPersonTotal": 54145,
    "InPersonDem": 27417,
    "InPersonRep": 25990,
    "InPersonUnknown": 738,
    "MailTotal": 4262,
    "MailDem": 3010,
    "MailRep": 1188,
    "MailUnknown": 64,
    "CumTotalReturned": 1046715,
    "CumInPersonTotal": 781180,
    "CumMailTotal": 265535,
    "CumInPersonDem": 401671,
    "CumInPersonRep": 370737,
    "CumInPersonUnknown": 8772,
    "CumMailDem": 191551,
    "CumMailRep": 71839,
    "CumMailUnknown": 2145
  },
  {
    "ReturnDate": "2026-04-15",
    "DayOfWeek": "Wednesday",
    "TotalReturned": 58410,
    "InPersonTotal": 54002,
    "InPersonDem": 27295,
    "InPersonRep": 25935,
    "InPersonUnknown": 772,
    "MailTotal": 4408,
    "MailDem": 3191,
    "MailRep": 1156,
    "MailUnknown": 61,
    "CumTotalReturned": 1105125,
    "CumInPersonTotal": 835182,
    "CumMailTotal": 269943,
    "CumInPersonDem": 428966,
    "CumInPersonRep": 396672,
    "CumInPersonUnknown": 9544,
    "CumMailDem": 194742,
    "CumMailRep": 72995,
    "CumMailUnknown": 2206
  },
  {
    "ReturnDate": "2026-04-16",
    "DayOfWeek": "Thursday",
    "TotalReturned": 65371,
    "InPersonTotal": 59309,
    "InPersonDem": 29358,
    "InPersonRep": 29069,
    "InPersonUnknown": 882,
    "MailTotal": 6062,
    "MailDem": 4340,
    "MailRep": 1620,
    "MailUnknown": 102,
    "CumTotalReturned": 1170496,
    "CumInPersonTotal": 894491,
    "CumMailTotal": 276005,
    "CumInPersonDem": 458324,
    "CumInPersonRep": 425741,
    "CumInPersonUnknown": 10426,
    "CumMailDem": 199082,
    "CumMailRep": 74615,
    "CumMailUnknown": 2308
  },
  {
    "ReturnDate": "2026-04-17",
    "DayOfWeek": "Friday",
    "TotalReturned": 86843,
    "InPersonTotal": 81411,
    "InPersonDem": 39744,
    "InPersonRep": 40310,
    "InPersonUnknown": 1357,
    "MailTotal": 5432,
    "MailDem": 3850,
    "MailRep": 1485,
    "MailUnknown": 97,
    "CumTotalReturned": 1257339,
    "CumInPersonTotal": 975902,
    "CumMailTotal": 281437,
    "CumInPersonDem": 498068,
    "CumInPersonRep": 466051,
    "CumInPersonUnknown": 11783,
    "CumMailDem": 202932,
    "CumMailRep": 76100,
    "CumMailUnknown": 2405
  },
  {
    "ReturnDate": "2026-04-18",
    "DayOfWeek": "Saturday",
    "TotalReturned": 104815,
    "InPersonTotal": 100482,
    "InPersonDem": 59469,
    "InPersonRep": 39203,
    "InPersonUnknown": 1810,
    "MailTotal": 4333,
    "MailDem": 3226,
    "MailRep": 1044,
    "MailUnknown": 63,
    "CumTotalReturned": 1362154,
    "CumInPersonTotal": 1076384,
    "CumMailTotal": 285770,
    "CumInPersonDem": 557537,
    "CumInPersonRep": 505254,
    "CumInPersonUnknown": 13593,
    "CumMailDem": 206158,
    "CumMailRep": 77144,
    "CumMailUnknown": 2468
  },
  {
    "ReturnDate": "2026-04-19",
    "DayOfWeek": "Sunday",
    "TotalReturned": 169,
    "InPersonTotal": 0,
    "InPersonDem": 0,
    "InPersonRep": 0,
    "InPersonUnknown": 0,
    "MailTotal": 169,
    "MailDem": 147,
    "MailRep": 22,
    "MailUnknown": 0,
    "CumTotalReturned": 1362323,
    "CumInPersonTotal": 1076384,
    "CumMailTotal": 285939,
    "CumInPersonDem": 557537,
    "CumInPersonRep": 505254,
    "CumInPersonUnknown": 13593,
    "CumMailDem": 206305,
    "CumMailRep": 77166,
    "CumMailUnknown": 2468
  },
  {
    "ReturnDate": "2026-04-20",
    "DayOfWeek": "Monday",
    "TotalReturned": 9368,
    "InPersonTotal": 34,
    "InPersonDem": 12,
    "InPersonRep": 21,
    "InPersonUnknown": 1,
    "MailTotal": 9334,
    "MailDem": 6610,
    "MailRep": 2571,
    "MailUnknown": 153,
    "CumTotalReturned": 1371691,
    "CumInPersonTotal": 1076418,
    "CumMailTotal": 295273,
    "CumInPersonDem": 557549,
    "CumInPersonRep": 505275,
    "CumInPersonUnknown": 13594,
    "CumMailDem": 212915,
    "CumMailRep": 79737,
    "CumMailUnknown": 2621
  },
  {
    "ReturnDate": "2026-04-21",
    "DayOfWeek": "Tuesday",
    "TotalReturned": 11617,
    "InPersonTotal": 3,
    "InPersonDem": 0,
    "InPersonRep": 3,
    "InPersonUnknown": 0,
    "MailTotal": 11614,
    "MailDem": 8663,
    "MailRep": 2776,
    "MailUnknown": 175,
    "CumTotalReturned": 1383308,
    "CumInPersonTotal": 1076421,
    "CumMailTotal": 306887,
    "CumInPersonDem": 557549,
    "CumInPersonRep": 505278,
    "CumInPersonUnknown": 13594,
    "CumMailDem": 221578,
    "CumMailRep": 82513,
    "CumMailUnknown": 2796
  },
  {
    "ReturnDate": "2026-04-22",
    "DayOfWeek": "Wednesday",
    "TotalReturned": 5343,
    "InPersonTotal": 0,
    "InPersonDem": 0,
    "InPersonRep": 0,
    "InPersonUnknown": 0,
    "MailTotal": 5343,
    "MailDem": 3834,
    "MailRep": 1402,
    "MailUnknown": 107,
    "CumTotalReturned": 1388651,
    "CumInPersonTotal": 1076421,
    "CumMailTotal": 312230,
    "CumInPersonDem": 557549,
    "CumInPersonRep": 505278,
    "CumInPersonUnknown": 13594,
    "CumMailDem": 225412,
    "CumMailRep": 83915,
    "CumMailUnknown": 2903
  },
  {
    "ReturnDate": "2026-04-23",
    "DayOfWeek": "Thursday",
    "TotalReturned": 3679,
    "InPersonTotal": 0,
    "InPersonDem": 0,
    "InPersonRep": 0,
    "InPersonUnknown": 0,
    "MailTotal": 3679,
    "MailDem": 2669,
    "MailRep": 938,
    "MailUnknown": 72,
    "CumTotalReturned": 1392330,
    "CumInPersonTotal": 1076421,
    "CumMailTotal": 315909,
    "CumInPersonDem": 557549,
    "CumInPersonRep": 505278,
    "CumInPersonUnknown": 13594,
    "CumMailDem": 228081,
    "CumMailRep": 84853,
    "CumMailUnknown": 2975
  }
]